{"chords": [{"x": 65.79310344827586, "y": "C"}, {"x": 57.195402298850574, "y": "G"}, {"x": 51.67816091954023, "y": "F"}, {"x": 37.97701149425287, "y": "Am"}, {"x": 35.81609195402299, "y": "D"}, {"x": 27.35632183908046, "y": "Em"}, {"x": 24.7816091954023, "y": "Dm"}, {"x": 20.413793103448278, "y": "A"}, {"x": 19.310344827586206, "y": "G7"}, {"x": 18.942528735632184, "y": "D7"}, {"x": 18.022988505747126, "y": "Bb"}, {"x": 14.39080459770115, "y": "E7"}, {"x": 14.160919540229886, "y": "A7"}, {"x": 12.689655172413794, "y": "C7"}, {"x": 11.586206896551724, "y": "Bm"}], "chord_combinations": [{"x": 44.64367816091954, "y": "C - G"}, {"x": 40.96551724137931, "y": "C - F"}, {"x": 31.95402298850575, "y": "Am - C"}, {"x": 28.275862068965516, "y": "D - G"}, {"x": 28.229885057471265, "y": "F - G"}, {"x": 28.04597701149425, "y": "Am - G"}, {"x": 25.74712643678161, "y": "Am - F"}, {"x": 23.264367816091955, "y": "Em - G"}, {"x": 22.75862068965517, "y": "C - D"}, {"x": 21.839080459770116, "y": "C - Em"}, {"x": 19.862068965517242, "y": "Dm - F"}, {"x": 18.942528735632184, "y": "C - Dm"}, {"x": 17.24137931034483, "y": "D - Em"}, {"x": 15.218390804597702, "y": "C - G7"}, {"x": 14.89655172413793, "y": "A - D"}], "chord_counts": [{"val": 8}, {"val": 10}, {"val": 5}, {"val": 8}, {"val": 6}, {"val": 13}, {"val": 5}, {"val": 4}, {"val": 7}, {"val": 3}, {"val": 3}, {"val": 9}, {"val": 11}, {"val": 4}, {"val": 9}, {"val": 4}, {"val": 7}, {"val": 15}, {"val": 8}, {"val": 11}, {"val": 4}, {"val": 7}, {"val": 7}, {"val": 7}, {"val": 3}, {"val": 8}, {"val": 5}, {"val": 3}, {"val": 10}, {"val": 5}, {"val": 6}, {"val": 7}, {"val": 5}, {"val": 12}, {"val": 5}, {"val": 9}, {"val": 14}, {"val": 10}, {"val": 6}, {"val": 11}, {"val": 5}, {"val": 7}, {"val": 10}, {"val": 9}, {"val": 4}, {"val": 12}, {"val": 7}, {"val": 6}, {"val": 4}, {"val": 3}, {"val": 4}, {"val": 7}, {"val": 3}, {"val": 5}, {"val": 11}, {"val": 4}, {"val": 5}, {"val": 17}, {"val": 6}, {"val": 3}, {"val": 6}, {"val": 4}, {"val": 5}, {"val": 10}, {"val": 4}, {"val": 4}, {"val": 3}, {"val": 7}, {"val": 8}, {"val": 3}, {"val": 5}, {"val": 7}, {"val": 10}, {"val": 4}, {"val": 4}, {"val": 10}, {"val": 5}, {"val": 5}, {"val": 6}, {"val": 6}, {"val": 10}, {"val": 6}, {"val": 6}, {"val": 6}, {"val": 7}, {"val": 4}, {"val": 16}, {"val": 5}, {"val": 16}, {"val": 14}, {"val": 8}, {"val": 4}, {"val": 4}, {"val": 4}, {"val": 10}, {"val": 10}, {"val": 7}, {"val": 6}, {"val": 5}, {"val": 2}, {"val": 4}, {"val": 5}, {"val": 15}, {"val": 4}, {"val": 3}, {"val": 3}, {"val": 5}, {"val": 9}, {"val": 3}, {"val": 7}, {"val": 12}, {"val": 13}, {"val": 5}, {"val": 4}, {"val": 3}, {"val": 3}, {"val": 3}, {"val": 12}, {"val": 6}, {"val": 5}, {"val": 6}, {"val": 7}, {"val": 7}, {"val": 11}, {"val": 9}, {"val": 6}, {"val": 15}, {"val": 8}, {"val": 4}, {"val": 7}, {"val": 14}, {"val": 10}, {"val": 7}, {"val": 8}, {"val": 8}, {"val": 16}, {"val": 19}, {"val": 5}, {"val": 4}, {"val": 4}, {"val": 11}, {"val": 10}, {"val": 12}, {"val": 5}, {"val": 4}, {"val": 9}, {"val": 4}, {"val": 8}, {"val": 7}, {"val": 3}, {"val": 12}, {"val": 6}, {"val": 5}, {"val": 4}, {"val": 18}, {"val": 23}, {"val": 4}, {"val": 3}, {"val": 3}, {"val": 5}, {"val": 12}, {"val": 5}, {"val": 13}, {"val": 12}, {"val": 7}, {"val": 4}, {"val": 10}, {"val": 13}, {"val": 5}, {"val": 18}, {"val": 5}, {"val": 8}, {"val": 4}, {"val": 6}, {"val": 9}, {"val": 11}, {"val": 7}, {"val": 5}, {"val": 6}, {"val": 6}, {"val": 11}, {"val": 3}, {"val": 10}, {"val": 3}, {"val": 5}, {"val": 9}, {"val": 10}, {"val": 10}, {"val": 3}, {"val": 13}, {"val": 5}, {"val": 6}, {"val": 7}, {"val": 5}, {"val": 5}, {"val": 4}, {"val": 16}, {"val": 3}, {"val": 6}, {"val": 3}, {"val": 5}, {"val": 4}, {"val": 3}, {"val": 7}, {"val": 4}, {"val": 9}, {"val": 8}, {"val": 7}, {"val": 6}, {"val": 4}, {"val": 13}, {"val": 15}, {"val": 13}, {"val": 5}, {"val": 4}, {"val": 6}, {"val": 6}, {"val": 10}, {"val": 12}, {"val": 5}, {"val": 6}, {"val": 11}, {"val": 7}, {"val": 4}, {"val": 12}, {"val": 12}, {"val": 3}, {"val": 5}, {"val": 7}, {"val": 11}, {"val": 5}, {"val": 8}, {"val": 5}, {"val": 12}, {"val": 5}, {"val": 6}, {"val": 10}, {"val": 4}, {"val": 9}, {"val": 8}, {"val": 3}, {"val": 7}, {"val": 9}, {"val": 13}, {"val": 4}, {"val": 12}, {"val": 3}, {"val": 5}, {"val": 2}, {"val": 4}, {"val": 11}, {"val": 3}, {"val": 20}, {"val": 8}, {"val": 3}, {"val": 6}, {"val": 4}, {"val": 7}, {"val": 4}, {"val": 4}, {"val": 7}, {"val": 3}, {"val": 13}, {"val": 5}, {"val": 4}, {"val": 8}, {"val": 7}, {"val": 11}, {"val": 5}, {"val": 4}, {"val": 6}, {"val": 5}, {"val": 8}, {"val": 3}, {"val": 4}, {"val": 15}, {"val": 4}, {"val": 3}, {"val": 6}, {"val": 9}, {"val": 6}, {"val": 9}, {"val": 6}, {"val": 3}, {"val": 12}, {"val": 5}, {"val": 5}, {"val": 5}, {"val": 4}, {"val": 10}, {"val": 5}, {"val": 10}, {"val": 6}, {"val": 9}, {"val": 12}, {"val": 13}, {"val": 5}, {"val": 6}, {"val": 17}, {"val": 6}, {"val": 7}, {"val": 11}, {"val": 19}, {"val": 7}, {"val": 3}, {"val": 5}, {"val": 8}, {"val": 7}, {"val": 6}, {"val": 10}, {"val": 13}, {"val": 7}, {"val": 3}, {"val": 7}, {"val": 13}, {"val": 5}, {"val": 12}, {"val": 4}, {"val": 7}, {"val": 11}, {"val": 9}, {"val": 7}, {"val": 4}, {"val": 14}, {"val": 3}, {"val": 7}, {"val": 13}, {"val": 7}, {"val": 4}, {"val": 15}, {"val": 9}, {"val": 3}, {"val": 5}, {"val": 3}, {"val": 7}, {"val": 9}, {"val": 15}, {"val": 8}, {"val": 3}, {"val": 7}, {"val": 4}, {"val": 13}, {"val": 2}, {"val": 4}, {"val": 3}, {"val": 5}, {"val": 4}, {"val": 6}, {"val": 7}, {"val": 8}, {"val": 3}, {"val": 14}, {"val": 9}, {"val": 17}, {"val": 9}, {"val": 5}, {"val": 19}, {"val": 4}, {"val": 6}, {"val": 8}, {"val": 8}, {"val": 12}, {"val": 12}, {"val": 10}, {"val": 6}, {"val": 4}, {"val": 5}, {"val": 5}, {"val": 10}, {"val": 18}, {"val": 11}, {"val": 5}, {"val": 5}, {"val": 6}, {"val": 12}, {"val": 5}, {"val": 6}, {"val": 17}, {"val": 8}, {"val": 2}, {"val": 4}, {"val": 11}, {"val": 7}, {"val": 12}, {"val": 9}, {"val": 8}, {"val": 5}, {"val": 5}, {"val": 4}, {"val": 4}, {"val": 12}, {"val": 5}, {"val": 15}, {"val": 11}, {"val": 5}, {"val": 7}, {"val": 4}, {"val": 6}, {"val": 9}, {"val": 1}, {"val": 6}, {"val": 7}, {"val": 6}, {"val": 4}, {"val": 4}, {"val": 7}, {"val": 5}, {"val": 9}, {"val": 5}, {"val": 5}, {"val": 5}, {"val": 3}, {"val": 2}, {"val": 3}, {"val": 5}, {"val": 6}, {"val": 9}, {"val": 9}, {"val": 8}, {"val": 4}, {"val": 7}, {"val": 9}, {"val": 7}, {"val": 3}, {"val": 8}, {"val": 12}, {"val": 12}, {"val": 12}, {"val": 4}, {"val": 3}, {"val": 3}, {"val": 2}, {"val": 5}, {"val": 16}, {"val": 10}, {"val": 7}, {"val": 9}, {"val": 5}, {"val": 7}, {"val": 5}, {"val": 20}, {"val": 8}, {"val": 14}, {"val": 5}, {"val": 4}, {"val": 4}, {"val": 8}, {"val": 3}, {"val": 4}, {"val": 5}, {"val": 9}, {"val": 15}, {"val": 7}, {"val": 12}, {"val": 2}, {"val": 7}, {"val": 7}, {"val": 3}, {"val": 3}, {"val": 5}, {"val": 4}, {"val": 11}, {"val": 11}, {"val": 10}, {"val": 24}, {"val": 4}, {"val": 8}, {"val": 6}, {"val": 15}, {"val": 10}, {"val": 5}, {"val": 10}, {"val": 9}, {"val": 4}, {"val": 6}, {"val": 4}, {"val": 6}, {"val": 4}, {"val": 17}, {"val": 9}, {"val": 5}, {"val": 4}, {"val": 9}, {"val": 5}, {"val": 5}, {"val": 11}, {"val": 4}, {"val": 5}, {"val": 5}, {"val": 8}, {"val": 5}, {"val": 8}, {"val": 8}, {"val": 9}, {"val": 7}, {"val": 5}, {"val": 9}, {"val": 4}, {"val": 12}, {"val": 4}, {"val": 7}, {"val": 3}, {"val": 9}, {"val": 4}, {"val": 4}, {"val": 14}, {"val": 9}, {"val": 3}, {"val": 6}, {"val": 6}, {"val": 15}, {"val": 7}, {"val": 6}, {"val": 11}, {"val": 13}, {"val": 5}, {"val": 7}, {"val": 7}, {"val": 4}, {"val": 4}, {"val": 7}, {"val": 9}, {"val": 9}, {"val": 10}, {"val": 7}, {"val": 7}, {"val": 17}, {"val": 4}, {"val": 8}, {"val": 3}, {"val": 3}, {"val": 15}, {"val": 7}, {"val": 5}, {"val": 6}, {"val": 7}, {"val": 7}, {"val": 7}, {"val": 6}, {"val": 9}, {"val": 6}, {"val": 16}, {"val": 5}, {"val": 5}, {"val": 5}, {"val": 10}, {"val": 5}, {"val": 5}, {"val": 4}, {"val": 4}, {"val": 19}, {"val": 9}, {"val": 10}, {"val": 12}, {"val": 3}, {"val": 14}, {"val": 4}, {"val": 6}, {"val": 6}, {"val": 8}, {"val": 9}, {"val": 8}, {"val": 11}, {"val": 11}, {"val": 4}, {"val": 9}, {"val": 4}, {"val": 5}, {"val": 4}, {"val": 7}, {"val": 4}, {"val": 14}, {"val": 7}, {"val": 2}, {"val": 2}, {"val": 10}, {"val": 7}, {"val": 4}, {"val": 2}, {"val": 5}, {"val": 8}, {"val": 2}, {"val": 4}, {"val": 4}, {"val": 17}, {"val": 4}, {"val": 14}, {"val": 3}, {"val": 5}, {"val": 6}, {"val": 5}, {"val": 4}, {"val": 6}, {"val": 2}, {"val": 12}, {"val": 7}, {"val": 2}, {"val": 6}, {"val": 5}, {"val": 3}, {"val": 4}, {"val": 4}, {"val": 4}, {"val": 5}, {"val": 12}, {"val": 9}, {"val": 7}, {"val": 3}, {"val": 3}, {"val": 3}, {"val": 4}, {"val": 2}, {"val": 6}, {"val": 9}, {"val": 6}, {"val": 5}, {"val": 11}, {"val": 5}, {"val": 5}, {"val": 9}, {"val": 2}, {"val": 5}, {"val": 7}, {"val": 8}, {"val": 7}, {"val": 9}, {"val": 6}, {"val": 3}, {"val": 4}, {"val": 8}, {"val": 7}, {"val": 21}, {"val": 4}, {"val": 3}, {"val": 5}, {"val": 13}, {"val": 6}, {"val": 4}, {"val": 8}, {"val": 4}, {"val": 4}, {"val": 6}, {"val": 5}, {"val": 6}, {"val": 7}, {"val": 8}, {"val": 4}, {"val": 5}, {"val": 4}, {"val": 7}, {"val": 4}, {"val": 9}, {"val": 6}, {"val": 11}, {"val": 12}, {"val": 4}, {"val": 4}, {"val": 26}, {"val": 4}, {"val": 6}, {"val": 4}, {"val": 4}, {"val": 5}, {"val": 5}, {"val": 5}, {"val": 13}, {"val": 9}, {"val": 9}, {"val": 7}, {"val": 5}, {"val": 4}, {"val": 5}, {"val": 12}, {"val": 7}, {"val": 3}, {"val": 5}, {"val": 7}, {"val": 4}, {"val": 10}, {"val": 4}, {"val": 4}, {"val": 8}, {"val": 7}, {"val": 8}, {"val": 6}, {"val": 4}, {"val": 4}, {"val": 6}, {"val": 5}, {"val": 11}, {"val": 9}, {"val": 7}, {"val": 7}, {"val": 7}, {"val": 9}, {"val": 4}, {"val": 5}, {"val": 4}, {"val": 5}, {"val": 5}, {"val": 5}, {"val": 4}, {"val": 6}, {"val": 6}, {"val": 11}, {"val": 5}, {"val": 4}, {"val": 9}, {"val": 4}, {"val": 6}, {"val": 9}, {"val": 3}, {"val": 6}, {"val": 9}, {"val": 14}, {"val": 7}, {"val": 5}, {"val": 8}, {"val": 6}, {"val": 8}, {"val": 5}, {"val": 9}, {"val": 10}, {"val": 4}, {"val": 5}, {"val": 9}, {"val": 6}, {"val": 7}, {"val": 13}, {"val": 7}, {"val": 4}, {"val": 7}, {"val": 4}, {"val": 4}, {"val": 6}, {"val": 10}, {"val": 6}, {"val": 4}, {"val": 11}, {"val": 3}, {"val": 5}, {"val": 8}, {"val": 5}, {"val": 8}, {"val": 7}, {"val": 6}, {"val": 7}, {"val": 8}, {"val": 4}, {"val": 4}, {"val": 4}, {"val": 21}, {"val": 4}, {"val": 3}, {"val": 4}, {"val": 3}, {"val": 5}, {"val": 6}, {"val": 11}, {"val": 4}, {"val": 9}, {"val": 3}, {"val": 5}, {"val": 10}, {"val": 4}, {"val": 5}, {"val": 7}, {"val": 10}, {"val": 4}, {"val": 6}, {"val": 4}, {"val": 4}, {"val": 8}, {"val": 11}, {"val": 11}, {"val": 7}, {"val": 5}, {"val": 6}, {"val": 7}, {"val": 4}, {"val": 6}, {"val": 3}, {"val": 11}, {"val": 4}, {"val": 4}, {"val": 3}, {"val": 4}, {"val": 9}, {"val": 7}, {"val": 6}, {"val": 6}, {"val": 5}, {"val": 7}, {"val": 3}, {"val": 8}, {"val": 8}, {"val": 12}, {"val": 7}, {"val": 3}, {"val": 27}, {"val": 4}, {"val": 5}, {"val": 2}, {"val": 4}, {"val": 12}, {"val": 5}, {"val": 17}, {"val": 5}, {"val": 14}, {"val": 3}, {"val": 7}, {"val": 11}, {"val": 7}, {"val": 6}, {"val": 12}, {"val": 6}, {"val": 3}, {"val": 11}, {"val": 10}, {"val": 4}, {"val": 5}, {"val": 7}, {"val": 5}, {"val": 11}, {"val": 6}, {"val": 6}, {"val": 4}, {"val": 4}, {"val": 14}, {"val": 4}, {"val": 6}, {"val": 5}, {"val": 5}, {"val": 6}, {"val": 7}, {"val": 7}, {"val": 7}, {"val": 5}, {"val": 7}, {"val": 13}, {"val": 3}, {"val": 17}, {"val": 5}, {"val": 13}, {"val": 5}, {"val": 19}, {"val": 14}, {"val": 10}, {"val": 6}, {"val": 9}, {"val": 4}, {"val": 5}, {"val": 4}, {"val": 7}, {"val": 5}, {"val": 5}, {"val": 5}, {"val": 4}, {"val": 10}, {"val": 4}, {"val": 4}, {"val": 6}, {"val": 5}, {"val": 7}, {"val": 6}, {"val": 5}, {"val": 4}, {"val": 10}, {"val": 6}, {"val": 4}, {"val": 12}, {"val": 18}, {"val": 7}, {"val": 5}, {"val": 5}, {"val": 10}, {"val": 6}, {"val": 5}, {"val": 15}, {"val": 19}, {"val": 11}, {"val": 8}, {"val": 10}, {"val": 10}, {"val": 3}, {"val": 3}, {"val": 10}, {"val": 8}, {"val": 9}, {"val": 6}, {"val": 4}, {"val": 12}, {"val": 5}, {"val": 18}, {"val": 7}, {"val": 5}, {"val": 8}, {"val": 8}, {"val": 4}, {"val": 5}, {"val": 4}, {"val": 4}, {"val": 8}, {"val": 6}, {"val": 12}, {"val": 7}, {"val": 6}, {"val": 7}, {"val": 6}, {"val": 7}, {"val": 6}, {"val": 10}, {"val": 8}, {"val": 3}, {"val": 8}, {"val": 8}, {"val": 3}, {"val": 5}, {"val": 6}, {"val": 8}, {"val": 7}, {"val": 3}, {"val": 3}, {"val": 3}, {"val": 11}, {"val": 7}, {"val": 19}, {"val": 4}, {"val": 4}, {"val": 10}, {"val": 6}, {"val": 4}, {"val": 5}, {"val": 3}, {"val": 12}, {"val": 7}, {"val": 9}, {"val": 8}, {"val": 5}, {"val": 3}, {"val": 4}, {"val": 4}, {"val": 3}, {"val": 6}, {"val": 4}, {"val": 5}, {"val": 7}, {"val": 7}, {"val": 5}, {"val": 4}, {"val": 4}, {"val": 8}, {"val": 5}, {"val": 7}, {"val": 5}, {"val": 3}, {"val": 6}, {"val": 2}, {"val": 3}, {"val": 2}, {"val": 3}, {"val": 6}, {"val": 7}, {"val": 2}, {"val": 2}, {"val": 5}, {"val": 6}, {"val": 3}, {"val": 4}, {"val": 9}, {"val": 7}, {"val": 2}, {"val": 2}, {"val": 2}, {"val": 3}, {"val": 5}, {"val": 5}, {"val": 4}, {"val": 6}, {"val": 8}, {"val": 4}, {"val": 5}, {"val": 3}, {"val": 15}, {"val": 1}, {"val": 6}, {"val": 4}, {"val": 7}, {"val": 5}, {"val": 10}, {"val": 5}, {"val": 3}, {"val": 9}, {"val": 2}, {"val": 4}, {"val": 7}, {"val": 7}, {"val": 9}, {"val": 6}, {"val": 4}, {"val": 11}, {"val": 6}, {"val": 4}, {"val": 8}, {"val": 24}, {"val": 4}, {"val": 5}, {"val": 4}, {"val": 3}, {"val": 10}, {"val": 11}, {"val": 3}, {"val": 9}, {"val": 7}, {"val": 6}, {"val": 11}, {"val": 11}, {"val": 6}, {"val": 5}, {"val": 4}, {"val": 4}, {"val": 9}, {"val": 6}, {"val": 4}, {"val": 9}, {"val": 9}, {"val": 9}, {"val": 7}, {"val": 3}, {"val": 4}, {"val": 5}, {"val": 2}, {"val": 4}, {"val": 4}, {"val": 7}, {"val": 12}, {"val": 3}, {"val": 8}, {"val": 5}, {"val": 4}, {"val": 1}, {"val": 4}, {"val": 4}, {"val": 4}, {"val": 10}, {"val": 7}, {"val": 5}, {"val": 3}, {"val": 8}, {"val": 9}, {"val": 4}, {"val": 6}, {"val": 11}, {"val": 5}, {"val": 8}, {"val": 3}, {"val": 6}, {"val": 11}, {"val": 2}, {"val": 5}, {"val": 3}, {"val": 6}, {"val": 6}, {"val": 9}, {"val": 5}, {"val": 3}, {"val": 5}, {"val": 17}, {"val": 2}, {"val": 7}, {"val": 4}, {"val": 11}, {"val": 9}, {"val": 9}, {"val": 5}, {"val": 6}, {"val": 7}, {"val": 7}, {"val": 10}, {"val": 4}, {"val": 4}, {"val": 5}, {"val": 8}, {"val": 4}, {"val": 2}, {"val": 4}, {"val": 11}, {"val": 5}, {"val": 4}, {"val": 3}, {"val": 3}, {"val": 5}, {"val": 9}, {"val": 7}, {"val": 4}, {"val": 12}, {"val": 4}, {"val": 2}, {"val": 5}, {"val": 5}, {"val": 7}, {"val": 6}, {"val": 9}, {"val": 5}, {"val": 4}, {"val": 3}, {"val": 4}, {"val": 10}, {"val": 3}, {"val": 3}, {"val": 8}, {"val": 2}, {"val": 4}, {"val": 7}, {"val": 10}, {"val": 4}, {"val": 5}, {"val": 8}, {"val": 4}, {"val": 5}, {"val": 6}, {"val": 5}, {"val": 6}, {"val": 3}, {"val": 7}, {"val": 8}, {"val": 3}, {"val": 6}, {"val": 4}, {"val": 3}, {"val": 3}, {"val": 4}, {"val": 5}, {"val": 8}, {"val": 2}, {"val": 7}, {"val": 3}, {"val": 4}, {"val": 7}, {"val": 5}, {"val": 2}, {"val": 3}, {"val": 4}, {"val": 6}, {"val": 6}, {"val": 3}, {"val": 5}, {"val": 2}, {"val": 3}, {"val": 4}, {"val": 8}, {"val": 4}, {"val": 6}, {"val": 6}, {"val": 7}, {"val": 3}, {"val": 2}, {"val": 6}, {"val": 5}, {"val": 6}, {"val": 3}, {"val": 4}, {"val": 7}, {"val": 5}, {"val": 5}, {"val": 5}, {"val": 4}, {"val": 3}, {"val": 4}, {"val": 4}, {"val": 3}, {"val": 4}, {"val": 3}, {"val": 5}, {"val": 6}, {"val": 5}, {"val": 3}, {"val": 3}, {"val": 2}, {"val": 7}, {"val": 3}, {"val": 5}, {"val": 4}, {"val": 2}, {"val": 4}, {"val": 4}, {"val": 6}, {"val": 3}, {"val": 4}, {"val": 3}, {"val": 4}, {"val": 4}, {"val": 3}, {"val": 3}, {"val": 2}, {"val": 3}, {"val": 2}, {"val": 3}, {"val": 4}, {"val": 7}, {"val": 4}, {"val": 3}, {"val": 5}, {"val": 4}, {"val": 4}, {"val": 6}, {"val": 6}, {"val": 8}, {"val": 4}, {"val": 7}, {"val": 1}, {"val": 8}, {"val": 3}, {"val": 4}, {"val": 4}, {"val": 6}, {"val": 4}, {"val": 6}, {"val": 6}, {"val": 4}, {"val": 4}, {"val": 4}, {"val": 6}, {"val": 3}, {"val": 4}, {"val": 4}, {"val": 3}, {"val": 11}, {"val": 10}, {"val": 3}, {"val": 4}, {"val": 4}, {"val": 4}, {"val": 6}, {"val": 3}, {"val": 2}, {"val": 4}, {"val": 3}, {"val": 4}, {"val": 3}, {"val": 6}, {"val": 4}, {"val": 4}, {"val": 4}, {"val": 4}, {"val": 3}, {"val": 5}, {"val": 3}, {"val": 2}, {"val": 4}, {"val": 12}, {"val": 6}, {"val": 4}, {"val": 2}, {"val": 5}, {"val": 9}, {"val": 4}, {"val": 6}, {"val": 3}, {"val": 5}, {"val": 3}, {"val": 4}, {"val": 6}, {"val": 4}, {"val": 4}, {"val": 4}, {"val": 4}, {"val": 5}, {"val": 5}, {"val": 6}, {"val": 8}, {"val": 3}, {"val": 6}, {"val": 4}, {"val": 6}, {"val": 10}, {"val": 3}, {"val": 3}, {"val": 5}, {"val": 6}, {"val": 6}, {"val": 3}, {"val": 3}, {"val": 4}, {"val": 4}, {"val": 6}, {"val": 6}, {"val": 3}, {"val": 5}, {"val": 5}, {"val": 7}, {"val": 5}, {"val": 4}, {"val": 7}, {"val": 5}, {"val": 4}, {"val": 4}, {"val": 6}, {"val": 6}, {"val": 4}, {"val": 7}, {"val": 4}, {"val": 4}, {"val": 4}, {"val": 4}, {"val": 7}, {"val": 4}, {"val": 6}, {"val": 7}, {"val": 5}, {"val": 5}, {"val": 3}, {"val": 4}, {"val": 4}, {"val": 4}, {"val": 8}, {"val": 7}, {"val": 7}, {"val": 4}, {"val": 4}, {"val": 8}, {"val": 5}, {"val": 5}, {"val": 5}, {"val": 3}, {"val": 9}, {"val": 9}, {"val": 6}, {"val": 4}, {"val": 3}, {"val": 5}, {"val": 5}, {"val": 5}, {"val": 5}, {"val": 7}, {"val": 5}, {"val": 15}, {"val": 4}, {"val": 6}, {"val": 2}, {"val": 5}, {"val": 9}, {"val": 6}, {"val": 7}, {"val": 6}, {"val": 12}, {"val": 18}, {"val": 5}, {"val": 11}, {"val": 9}, {"val": 10}, {"val": 13}, {"val": 10}, {"val": 4}, {"val": 7}, {"val": 5}, {"val": 4}, {"val": 10}, {"val": 3}, {"val": 3}, {"val": 16}, {"val": 6}, {"val": 4}, {"val": 4}, {"val": 5}, {"val": 5}, {"val": 10}, {"val": 8}, {"val": 8}, {"val": 7}, {"val": 11}, {"val": 8}, {"val": 13}, {"val": 5}, {"val": 6}, {"val": 6}, {"val": 18}, {"val": 4}, {"val": 7}, {"val": 12}, {"val": 4}, {"val": 6}, {"val": 4}, {"val": 6}, {"val": 3}, {"val": 6}, {"val": 11}, {"val": 3}, {"val": 8}, {"val": 5}, {"val": 5}, {"val": 4}, {"val": 3}, {"val": 4}, {"val": 3}, {"val": 6}, {"val": 2}, {"val": 3}, {"val": 2}, {"val": 2}, {"val": 6}, {"val": 4}, {"val": 4}, {"val": 4}, {"val": 5}, {"val": 4}, {"val": 8}, {"val": 5}, {"val": 5}, {"val": 5}, {"val": 7}, {"val": 4}, {"val": 4}, {"val": 4}, {"val": 4}, {"val": 4}, {"val": 6}, {"val": 13}, {"val": 5}, {"val": 7}, {"val": 5}, {"val": 5}, {"val": 3}, {"val": 9}, {"val": 6}, {"val": 7}, {"val": 6}, {"val": 7}, {"val": 4}, {"val": 4}, {"val": 4}, {"val": 2}, {"val": 1}, {"val": 5}, {"val": 5}, {"val": 1}, {"val": 4}, {"val": 2}, {"val": 2}, {"val": 6}, {"val": 4}, {"val": 4}, {"val": 2}, {"val": 2}, {"val": 3}, {"val": 3}, {"val": 2}, {"val": 2}, {"val": 3}, {"val": 2}, {"val": 7}, {"val": 5}, {"val": 4}, {"val": 8}, {"val": 2}, {"val": 2}, {"val": 7}, {"val": 3}, {"val": 4}, {"val": 5}, {"val": 4}, {"val": 4}, {"val": 5}, {"val": 5}, {"val": 5}, {"val": 2}, {"val": 12}, {"val": 4}, {"val": 7}, {"val": 5}, {"val": 7}, {"val": 6}, {"val": 6}, {"val": 10}, {"val": 5}, {"val": 6}, {"val": 5}, {"val": 4}, {"val": 5}, {"val": 3}, {"val": 3}, {"val": 4}, {"val": 4}, {"val": 7}, {"val": 6}, {"val": 3}, {"val": 6}, {"val": 12}, {"val": 6}, {"val": 4}, {"val": 2}, {"val": 5}, {"val": 2}, {"val": 5}, {"val": 5}, {"val": 3}, {"val": 3}, {"val": 9}, {"val": 5}, {"val": 6}, {"val": 3}, {"val": 4}, {"val": 13}, {"val": 8}, {"val": 8}, {"val": 4}, {"val": 4}, {"val": 4}, {"val": 7}, {"val": 4}, {"val": 3}, {"val": 4}, {"val": 4}, {"val": 9}, {"val": 4}, {"val": 4}, {"val": 5}, {"val": 6}, {"val": 3}, {"val": 5}, {"val": 4}, {"val": 4}, {"val": 4}, {"val": 3}, {"val": 5}, {"val": 5}, {"val": 7}, {"val": 6}, {"val": 3}, {"val": 5}, {"val": 5}, {"val": 4}, {"val": 5}, {"val": 4}, {"val": 10}, {"val": 4}, {"val": 3}, {"val": 4}, {"val": 6}, {"val": 5}, {"val": 13}, {"val": 5}, {"val": 6}, {"val": 7}, {"val": 3}, {"val": 5}, {"val": 5}, {"val": 4}, {"val": 5}, {"val": 3}, {"val": 1}, {"val": 5}, {"val": 7}, {"val": 5}, {"val": 6}, {"val": 4}, {"val": 4}, {"val": 4}, {"val": 3}, {"val": 8}, {"val": 10}, {"val": 5}, {"val": 5}, {"val": 10}, {"val": 4}, {"val": 2}, {"val": 3}, {"val": 5}, {"val": 6}, {"val": 8}, {"val": 3}, {"val": 3}, {"val": 4}, {"val": 6}, {"val": 3}, {"val": 4}, {"val": 6}, {"val": 4}, {"val": 4}, {"val": 6}, {"val": 5}, {"val": 3}, {"val": 6}, {"val": 7}, {"val": 6}, {"val": 5}, {"val": 4}, {"val": 5}, {"val": 4}, {"val": 3}, {"val": 4}, {"val": 4}, {"val": 3}, {"val": 1}, {"val": 4}, {"val": 4}, {"val": 10}, {"val": 10}, {"val": 7}, {"val": 5}, {"val": 7}, {"val": 3}, {"val": 3}, {"val": 4}, {"val": 5}, {"val": 7}, {"val": 4}, {"val": 6}, {"val": 9}, {"val": 7}, {"val": 4}, {"val": 4}, {"val": 6}, {"val": 1}, {"val": 9}, {"val": 7}, {"val": 5}, {"val": 8}, {"val": 3}, {"val": 3}, {"val": 1}, {"val": 1}, {"val": 5}, {"val": 3}, {"val": 5}, {"val": 6}, {"val": 7}, {"val": 7}, {"val": 4}, {"val": 3}, {"val": 3}, {"val": 4}, {"val": 4}, {"val": 4}, {"val": 1}, {"val": 4}, {"val": 4}, {"val": 5}, {"val": 5}, {"val": 9}, {"val": 1}, {"val": 4}, {"val": 4}, {"val": 4}, {"val": 6}, {"val": 5}, {"val": 14}, {"val": 8}, {"val": 9}, {"val": 6}, {"val": 6}, {"val": 5}, {"val": 3}, {"val": 5}, {"val": 4}, {"val": 3}, {"val": 11}, {"val": 12}, {"val": 7}, {"val": 7}, {"val": 9}, {"val": 5}, {"val": 4}, {"val": 3}, {"val": 9}, {"val": 13}, {"val": 9}, {"val": 4}, {"val": 3}, {"val": 8}, {"val": 4}, {"val": 4}, {"val": 8}, {"val": 4}, {"val": 4}, {"val": 3}, {"val": 5}, {"val": 4}, {"val": 4}, {"val": 6}, {"val": 4}, {"val": 3}, {"val": 4}, {"val": 7}, {"val": 5}, {"val": 3}, {"val": 8}, {"val": 8}, {"val": 4}, {"val": 8}, {"val": 6}, {"val": 18}, {"val": 7}, {"val": 9}, {"val": 6}, {"val": 10}, {"val": 6}, {"val": 5}, {"val": 5}, {"val": 3}, {"val": 6}, {"val": 5}, {"val": 4}, {"val": 5}, {"val": 4}, {"val": 2}, {"val": 4}, {"val": 5}, {"val": 4}, {"val": 5}, {"val": 3}, {"val": 5}, {"val": 5}, {"val": 10}, {"val": 6}, {"val": 3}, {"val": 4}, {"val": 7}, {"val": 4}, {"val": 4}, {"val": 4}, {"val": 4}, {"val": 4}, {"val": 7}, {"val": 8}, {"val": 3}, {"val": 4}, {"val": 5}, {"val": 3}, {"val": 7}, {"val": 4}, {"val": 7}, {"val": 5}, {"val": 5}, {"val": 4}, {"val": 7}, {"val": 7}, {"val": 5}, {"val": 8}, {"val": 9}, {"val": 4}, {"val": 4}, {"val": 10}, {"val": 6}, {"val": 10}, {"val": 2}, {"val": 5}, {"val": 4}, {"val": 5}, {"val": 5}, {"val": 5}, {"val": 3}, {"val": 3}, {"val": 4}, {"val": 10}, {"val": 4}, {"val": 4}, {"val": 4}, {"val": 4}, {"val": 9}, {"val": 5}, {"val": 5}, {"val": 4}, {"val": 5}, {"val": 5}, {"val": 3}, {"val": 3}, {"val": 7}, {"val": 7}, {"val": 5}, {"val": 4}, {"val": 4}, {"val": 7}, {"val": 4}, {"val": 4}, {"val": 2}, {"val": 4}, {"val": 7}, {"val": 4}, {"val": 10}, {"val": 4}, {"val": 6}, {"val": 7}, {"val": 6}, {"val": 3}, {"val": 6}, {"val": 3}, {"val": 4}, {"val": 4}, {"val": 3}, {"val": 5}, {"val": 3}, {"val": 2}, {"val": 7}, {"val": 4}, {"val": 2}, {"val": 5}, {"val": 4}, {"val": 7}, {"val": 4}, {"val": 6}, {"val": 4}, {"val": 8}, {"val": 4}, {"val": 6}, {"val": 4}, {"val": 5}, {"val": 11}, {"val": 4}, {"val": 6}, {"val": 4}, {"val": 5}, {"val": 8}, {"val": 3}, {"val": 3}, {"val": 3}, {"val": 4}, {"val": 6}, {"val": 7}, {"val": 6}, {"val": 2}, {"val": 3}, {"val": 2}, {"val": 6}, {"val": 6}, {"val": 7}, {"val": 4}, {"val": 4}, {"val": 2}, {"val": 4}, {"val": 2}, {"val": 2}, {"val": 6}, {"val": 9}, {"val": 4}, {"val": 5}, {"val": 6}, {"val": 5}, {"val": 4}, {"val": 8}, {"val": 8}, {"val": 4}, {"val": 3}, {"val": 3}, {"val": 4}, {"val": 7}, {"val": 3}, {"val": 5}, {"val": 5}, {"val": 5}, {"val": 6}, {"val": 5}, {"val": 5}, {"val": 3}, {"val": 8}, {"val": 3}, {"val": 3}, {"val": 3}, {"val": 4}, {"val": 11}, {"val": 5}, {"val": 5}, {"val": 6}, {"val": 4}, {"val": 2}, {"val": 2}, {"val": 5}, {"val": 10}, {"val": 4}, {"val": 6}, {"val": 5}, {"val": 3}, {"val": 9}, {"val": 8}, {"val": 9}, {"val": 2}, {"val": 3}, {"val": 4}, {"val": 3}, {"val": 12}, {"val": 10}, {"val": 7}, {"val": 4}, {"val": 6}, {"val": 10}, {"val": 6}, {"val": 14}, {"val": 4}, {"val": 4}, {"val": 4}, {"val": 7}, {"val": 3}, {"val": 12}, {"val": 4}, {"val": 5}, {"val": 5}, {"val": 4}, {"val": 5}, {"val": 6}, {"val": 7}, {"val": 5}, {"val": 3}, {"val": 3}, {"val": 2}, {"val": 3}, {"val": 2}, {"val": 4}, {"val": 2}, {"val": 2}, {"val": 3}, {"val": 2}, {"val": 3}, {"val": 8}, {"val": 2}, {"val": 4}, {"val": 2}, {"val": 2}, {"val": 6}, {"val": 1}, {"val": 1}, {"val": 1}, {"val": 3}, {"val": 1}, {"val": 3}, {"val": 1}, {"val": 3}, {"val": 8}, {"val": 9}, {"val": 4}, {"val": 5}, {"val": 3}, {"val": 10}, {"val": 4}, {"val": 9}, {"val": 3}, {"val": 3}, {"val": 13}, {"val": 4}, {"val": 4}, {"val": 7}, {"val": 11}, {"val": 4}, {"val": 4}, {"val": 4}, {"val": 4}, {"val": 15}, {"val": 2}, {"val": 2}, {"val": 4}, {"val": 3}, {"val": 4}, {"val": 6}, {"val": 7}, {"val": 7}, {"val": 9}, {"val": 5}, {"val": 4}, {"val": 4}, {"val": 4}, {"val": 4}, {"val": 4}, {"val": 4}, {"val": 2}, {"val": 5}, {"val": 5}, {"val": 9}, {"val": 6}, {"val": 8}, {"val": 7}, {"val": 5}, {"val": 7}, {"val": 5}, {"val": 4}, {"val": 3}, {"val": 4}, {"val": 4}, {"val": 7}, {"val": 4}, {"val": 11}, {"val": 4}, {"val": 6}, {"val": 5}, {"val": 4}, {"val": 6}, {"val": 5}, {"val": 8}, {"val": 6}, {"val": 4}, {"val": 5}, {"val": 4}, {"val": 3}, {"val": 4}, {"val": 5}, {"val": 3}, {"val": 3}, {"val": 3}, {"val": 5}, {"val": 2}, {"val": 6}, {"val": 4}, {"val": 8}, {"val": 5}, {"val": 6}, {"val": 5}, {"val": 4}, {"val": 5}, {"val": 8}, {"val": 4}, {"val": 4}, {"val": 5}, {"val": 5}, {"val": 8}, {"val": 9}, {"val": 8}, {"val": 8}, {"val": 4}, {"val": 6}, {"val": 6}, {"val": 4}, {"val": 8}, {"val": 3}, {"val": 3}, {"val": 4}, {"val": 7}, {"val": 3}, {"val": 5}, {"val": 4}, {"val": 7}, {"val": 6}, {"val": 3}, {"val": 3}, {"val": 1}, {"val": 2}, {"val": 5}, {"val": 8}, {"val": 8}, {"val": 3}, {"val": 4}, {"val": 4}, {"val": 4}, {"val": 4}, {"val": 3}, {"val": 6}, {"val": 9}, {"val": 4}, {"val": 2}, {"val": 7}, {"val": 5}, {"val": 6}, {"val": 3}, {"val": 4}, {"val": 3}, {"val": 3}, {"val": 3}, {"val": 2}, {"val": 7}, {"val": 3}, {"val": 3}, {"val": 3}, {"val": 5}, {"val": 3}, {"val": 4}, {"val": 13}, {"val": 7}, {"val": 7}, {"val": 3}, {"val": 5}, {"val": 4}, {"val": 9}, {"val": 4}, {"val": 4}, {"val": 9}, {"val": 6}, {"val": 4}, {"val": 4}, {"val": 7}, {"val": 3}, {"val": 6}, {"val": 4}, {"val": 4}, {"val": 4}, {"val": 4}, {"val": 10}, {"val": 7}, {"val": 4}, {"val": 3}, {"val": 4}, {"val": 11}, {"val": 4}, {"val": 4}, {"val": 6}, {"val": 7}, {"val": 13}, {"val": 16}, {"val": 5}, {"val": 2}, {"val": 2}, {"val": 6}, {"val": 4}, {"val": 7}, {"val": 3}, {"val": 4}, {"val": 9}, {"val": 3}, {"val": 4}, {"val": 4}, {"val": 4}, {"val": 5}, {"val": 8}, {"val": 9}, {"val": 3}, {"val": 11}, {"val": 8}, {"val": 5}, {"val": 4}, {"val": 3}, {"val": 5}, {"val": 5}, {"val": 5}, {"val": 4}, {"val": 8}, {"val": 2}, {"val": 3}, {"val": 4}, {"val": 2}, {"val": 2}, {"val": 4}, {"val": 4}, {"val": 5}, {"val": 4}, {"val": 5}, {"val": 5}, {"val": 9}, {"val": 5}, {"val": 7}, {"val": 5}, {"val": 4}, {"val": 4}, {"val": 3}, {"val": 7}, {"val": 8}, {"val": 4}, {"val": 9}, {"val": 4}, {"val": 6}, {"val": 7}, {"val": 5}, {"val": 2}, {"val": 3}, {"val": 4}, {"val": 9}, {"val": 6}, {"val": 12}, {"val": 6}, {"val": 3}, {"val": 5}, {"val": 5}, {"val": 5}, {"val": 5}, {"val": 6}, {"val": 4}, {"val": 6}, {"val": 14}, {"val": 7}, {"val": 4}, {"val": 9}, {"val": 6}, {"val": 4}, {"val": 7}, {"val": 5}, {"val": 4}, {"val": 6}, {"val": 6}, {"val": 5}, {"val": 6}], "chord_sets": [{"x": 4.459770114942529, "y": "Am, C, F, G"}, {"x": 2.2988505747126435, "y": "C, D, Em, G"}, {"x": 1.793103448275862, "y": "C, F, G7"}, {"x": 1.7011494252873562, "y": "Am, C, Dm, F, G"}, {"x": 1.471264367816092, "y": "C, F, G"}, {"x": 1.103448275862069, "y": "Bb, C, Dm, F"}, {"x": 0.9195402298850575, "y": "C, F"}, {"x": 0.9195402298850575, "y": "Am, C, D, Em, G"}, {"x": 0.8275862068965517, "y": "C, D, G"}, {"x": 0.8275862068965517, "y": "Am, C, Em, F, G"}, {"x": 0.7816091954022989, "y": "A, Bm, D, G"}, {"x": 0.735632183908046, "y": "C, D7, G"}, {"x": 0.735632183908046, "y": "C, G7"}, {"x": 0.5977011494252874, "y": "Bm, C, D, Em, G"}, {"x": 0.5517241379310345, "y": "C, C7, F, G7"}], "keys": [{"x": 25.839080459770116, "y": "C"}, {"x": 19.126436781609197, "y": "G"}, {"x": 9.195402298850574, "y": "F"}, {"x": 6.942528735632184, "y": "D"}, {"x": 5.7011494252873565, "y": "Am"}, {"x": 4.32183908045977, "y": "A"}, {"x": 3.218390804597701, "y": "Dm"}, {"x": 2.6666666666666665, "y": "Em"}, {"x": 1.6091954022988506, "y": "Gm"}, {"x": 1.5632183908045978, "y": "E"}, {"x": 1.5172413793103448, "y": "Bb"}, {"x": 1.0114942528735633, "y": "Cm"}, {"x": 0.9655172413793104, "y": "Eb"}, {"x": 0.5057471264367817, "y": "Bm"}, {"x": 0.41379310344827586, "y": "F#m"}], "totals": {"chords": 335, "chord_sets": 1412, "keys": 29, "songs": 2175}}