{"chords": [{"x": 65.26351813826146, "y": "C"}, {"x": 56.639288158795345, "y": "G"}, {"x": 51.23203285420944, "y": "F"}, {"x": 38.60369609856263, "y": "Am"}, {"x": 36.61875427789185, "y": "D"}, {"x": 28.64476386036961, "y": "Em"}, {"x": 25.94113620807666, "y": "Dm"}, {"x": 20.396988364134156, "y": "A"}, {"x": 20.2258726899384, "y": "D7"}, {"x": 20.088980150581794, "y": "G7"}, {"x": 19.95208761122519, "y": "Bb"}, {"x": 15.537303216974674, "y": "A7"}, {"x": 14.955509924709103, "y": "E7"}, {"x": 13.620807665982204, "y": "C7"}, {"x": 12.97056810403833, "y": "Bm"}], "chord_combinations": [{"x": 44.31895961670089, "y": "C - G"}, {"x": 40.5201916495551, "y": "C - F"}, {"x": 32.375085557837096, "y": "Am - C"}, {"x": 28.507871321013006, "y": "D - G"}, {"x": 28.302532511978097, "y": "Am - G"}, {"x": 27.378507871321013, "y": "F - G"}, {"x": 25.633127994524298, "y": "Am - F"}, {"x": 24.469541409993155, "y": "Em - G"}, {"x": 23.169062286105408, "y": "C - D"}, {"x": 22.99794661190965, "y": "C - Em"}, {"x": 20.80766598220397, "y": "Dm - F"}, {"x": 19.78097193702943, "y": "C - Dm"}, {"x": 17.89869952087611, "y": "D - Em"}, {"x": 15.879534565366187, "y": "Bb - F"}, {"x": 15.263518138261464, "y": "C - G7"}], "chord_counts": [{"val": 8}, {"val": 17}, {"val": 26}, {"val": 10}, {"val": 4}, {"val": 6}, {"val": 5}, {"val": 9}, {"val": 7}, {"val": 4}, {"val": 9}, {"val": 8}, {"val": 3}, {"val": 10}, {"val": 8}, {"val": 8}, {"val": 22}, {"val": 5}, {"val": 10}, {"val": 13}, {"val": 6}, {"val": 4}, {"val": 9}, {"val": 5}, {"val": 6}, {"val": 5}, {"val": 4}, {"val": 7}, {"val": 7}, {"val": 8}, {"val": 7}, {"val": 11}, {"val": 9}, {"val": 8}, {"val": 6}, {"val": 19}, {"val": 6}, {"val": 5}, {"val": 7}, {"val": 6}, {"val": 4}, {"val": 5}, {"val": 4}, {"val": 7}, {"val": 5}, {"val": 7}, {"val": 6}, {"val": 8}, {"val": 7}, {"val": 6}, {"val": 10}, {"val": 10}, {"val": 9}, {"val": 6}, {"val": 5}, {"val": 19}, {"val": 9}, {"val": 9}, {"val": 8}, {"val": 5}, {"val": 9}, {"val": 6}, {"val": 7}, {"val": 6}, {"val": 3}, {"val": 8}, {"val": 4}, {"val": 6}, {"val": 4}, {"val": 4}, {"val": 4}, {"val": 9}, {"val": 16}, {"val": 9}, {"val": 6}, {"val": 5}, {"val": 8}, {"val": 5}, {"val": 21}, {"val": 10}, {"val": 5}, {"val": 4}, {"val": 9}, {"val": 7}, {"val": 7}, {"val": 6}, {"val": 6}, {"val": 13}, {"val": 4}, {"val": 6}, {"val": 5}, {"val": 13}, {"val": 22}, {"val": 9}, {"val": 4}, {"val": 11}, {"val": 7}, {"val": 5}, {"val": 5}, {"val": 5}, {"val": 5}, {"val": 3}, {"val": 6}, {"val": 16}, {"val": 5}, {"val": 8}, {"val": 9}, {"val": 11}, {"val": 9}, {"val": 3}, {"val": 6}, {"val": 5}, {"val": 4}, {"val": 6}, {"val": 18}, {"val": 4}, {"val": 4}, {"val": 8}, {"val": 9}, {"val": 9}, {"val": 4}, {"val": 5}, {"val": 6}, {"val": 8}, {"val": 5}, {"val": 19}, {"val": 8}, {"val": 8}, {"val": 4}, {"val": 5}, {"val": 3}, {"val": 9}, {"val": 10}, {"val": 10}, {"val": 7}, {"val": 7}, {"val": 21}, {"val": 4}, {"val": 14}, {"val": 9}, {"val": 6}, {"val": 3}, {"val": 3}, {"val": 8}, {"val": 7}, {"val": 7}, {"val": 4}, {"val": 5}, {"val": 11}, {"val": 19}, {"val": 3}, {"val": 9}, {"val": 6}, {"val": 7}, {"val": 7}, {"val": 4}, {"val": 12}, {"val": 11}, {"val": 11}, {"val": 6}, {"val": 6}, {"val": 8}, {"val": 10}, {"val": 7}, {"val": 9}, {"val": 4}, {"val": 16}, {"val": 4}, {"val": 5}, {"val": 6}, {"val": 6}, {"val": 5}, {"val": 3}, {"val": 13}, {"val": 4}, {"val": 6}, {"val": 4}, {"val": 6}, {"val": 8}, {"val": 12}, {"val": 10}, {"val": 5}, {"val": 5}, {"val": 6}, {"val": 14}, {"val": 11}, {"val": 5}, {"val": 4}, {"val": 8}, {"val": 11}, {"val": 26}, {"val": 7}, {"val": 10}, {"val": 6}, {"val": 6}, {"val": 6}, {"val": 7}, {"val": 5}, {"val": 5}, {"val": 4}, {"val": 5}, {"val": 8}, {"val": 5}, {"val": 8}, {"val": 3}, {"val": 4}, {"val": 17}, {"val": 10}, {"val": 4}, {"val": 8}, {"val": 8}, {"val": 3}, {"val": 5}, {"val": 4}, {"val": 9}, {"val": 9}, {"val": 9}, {"val": 4}, {"val": 7}, {"val": 5}, {"val": 10}, {"val": 15}, {"val": 7}, {"val": 6}, {"val": 13}, {"val": 6}, {"val": 4}, {"val": 7}, {"val": 6}, {"val": 6}, {"val": 8}, {"val": 28}, {"val": 5}, {"val": 5}, {"val": 8}, {"val": 11}, {"val": 6}, {"val": 8}, {"val": 8}, {"val": 10}, {"val": 6}, {"val": 11}, {"val": 18}, {"val": 9}, {"val": 7}, {"val": 4}, {"val": 3}, {"val": 6}, {"val": 6}, {"val": 10}, {"val": 17}, {"val": 2}, {"val": 20}, {"val": 6}, {"val": 29}, {"val": 13}, {"val": 6}, {"val": 16}, {"val": 12}, {"val": 5}, {"val": 8}, {"val": 5}, {"val": 6}, {"val": 6}, {"val": 9}, {"val": 6}, {"val": 16}, {"val": 4}, {"val": 5}, {"val": 7}, {"val": 5}, {"val": 5}, {"val": 7}, {"val": 4}, {"val": 6}, {"val": 7}, {"val": 4}, {"val": 22}, {"val": 5}, {"val": 7}, {"val": 4}, {"val": 15}, {"val": 4}, {"val": 4}, {"val": 5}, {"val": 5}, {"val": 8}, {"val": 8}, {"val": 4}, {"val": 4}, {"val": 4}, {"val": 9}, {"val": 7}, {"val": 3}, {"val": 6}, {"val": 6}, {"val": 5}, {"val": 11}, {"val": 7}, {"val": 6}, {"val": 5}, {"val": 8}, {"val": 3}, {"val": 6}, {"val": 6}, {"val": 20}, {"val": 9}, {"val": 6}, {"val": 6}, {"val": 8}, {"val": 15}, {"val": 6}, {"val": 14}, {"val": 10}, {"val": 4}, {"val": 15}, {"val": 7}, {"val": 7}, {"val": 8}, {"val": 8}, {"val": 3}, {"val": 4}, {"val": 6}, {"val": 4}, {"val": 4}, {"val": 18}, {"val": 6}, {"val": 4}, {"val": 6}, {"val": 4}, {"val": 16}, {"val": 5}, {"val": 6}, {"val": 5}, {"val": 3}, {"val": 8}, {"val": 6}, {"val": 7}, {"val": 28}, {"val": 5}, {"val": 6}, {"val": 4}, {"val": 3}, {"val": 11}, {"val": 6}, {"val": 5}, {"val": 7}, {"val": 7}, {"val": 5}, {"val": 19}, {"val": 6}, {"val": 15}, {"val": 8}, {"val": 5}, {"val": 13}, {"val": 15}, {"val": 7}, {"val": 7}, {"val": 8}, {"val": 8}, {"val": 10}, {"val": 7}, {"val": 5}, {"val": 4}, {"val": 4}, {"val": 5}, {"val": 18}, {"val": 7}, {"val": 6}, {"val": 3}, {"val": 11}, {"val": 11}, {"val": 7}, {"val": 7}, {"val": 11}, {"val": 5}, {"val": 5}, {"val": 7}, {"val": 22}, {"val": 5}, {"val": 5}, {"val": 4}, {"val": 3}, {"val": 5}, {"val": 6}, {"val": 5}, {"val": 7}, {"val": 10}, {"val": 10}, {"val": 7}, {"val": 5}, {"val": 4}, {"val": 5}, {"val": 5}, {"val": 19}, {"val": 15}, {"val": 9}, {"val": 5}, {"val": 8}, {"val": 7}, {"val": 24}, {"val": 6}, {"val": 7}, {"val": 12}, {"val": 4}, {"val": 3}, {"val": 11}, {"val": 12}, {"val": 3}, {"val": 14}, {"val": 7}, {"val": 13}, {"val": 6}, {"val": 7}, {"val": 4}, {"val": 15}, {"val": 6}, {"val": 15}, {"val": 7}, {"val": 16}, {"val": 17}, {"val": 8}, {"val": 11}, {"val": 4}, {"val": 16}, {"val": 6}, {"val": 4}, {"val": 8}, {"val": 13}, {"val": 14}, {"val": 11}, {"val": 8}, {"val": 2}, {"val": 8}, {"val": 5}, {"val": 4}, {"val": 4}, {"val": 3}, {"val": 10}, {"val": 18}, {"val": 7}, {"val": 9}, {"val": 4}, {"val": 7}, {"val": 10}, {"val": 10}, {"val": 3}, {"val": 4}, {"val": 4}, {"val": 17}, {"val": 3}, {"val": 4}, {"val": 10}, {"val": 4}, {"val": 8}, {"val": 4}, {"val": 6}, {"val": 14}, {"val": 9}, {"val": 7}, {"val": 4}, {"val": 9}, {"val": 10}, {"val": 6}, {"val": 8}, {"val": 2}, {"val": 7}, {"val": 7}, {"val": 5}, {"val": 16}, {"val": 5}, {"val": 5}, {"val": 22}, {"val": 6}, {"val": 9}, {"val": 11}, {"val": 2}, {"val": 7}, {"val": 10}, {"val": 9}, {"val": 5}, {"val": 4}, {"val": 27}, {"val": 8}, {"val": 5}, {"val": 12}, {"val": 6}, {"val": 10}, {"val": 15}, {"val": 21}, {"val": 5}, {"val": 4}, {"val": 7}, {"val": 17}, {"val": 4}, {"val": 6}, {"val": 4}, {"val": 4}, {"val": 10}, {"val": 19}, {"val": 10}, {"val": 7}, {"val": 10}, {"val": 7}, {"val": 10}, {"val": 8}, {"val": 10}, {"val": 1}, {"val": 24}, {"val": 6}, {"val": 15}, {"val": 5}, {"val": 22}, {"val": 4}, {"val": 4}, {"val": 6}, {"val": 11}, {"val": 8}, {"val": 4}, {"val": 7}, {"val": 8}, {"val": 30}, {"val": 7}, {"val": 5}, {"val": 5}, {"val": 5}, {"val": 5}, {"val": 7}, {"val": 6}, {"val": 19}, {"val": 20}, {"val": 6}, {"val": 6}, {"val": 6}, {"val": 5}, {"val": 9}, {"val": 10}, {"val": 6}, {"val": 5}, {"val": 4}, {"val": 10}, {"val": 7}, {"val": 10}, {"val": 16}, {"val": 14}, {"val": 8}, {"val": 4}, {"val": 4}, {"val": 5}, {"val": 8}, {"val": 11}, {"val": 8}, {"val": 6}, {"val": 9}, {"val": 5}, {"val": 4}, {"val": 5}, {"val": 5}, {"val": 10}, {"val": 5}, {"val": 8}, {"val": 10}, {"val": 6}, {"val": 5}, {"val": 2}, {"val": 5}, {"val": 6}, {"val": 6}, {"val": 11}, {"val": 6}, {"val": 12}, {"val": 7}, {"val": 4}, {"val": 9}, {"val": 6}, {"val": 6}, {"val": 5}, {"val": 4}, {"val": 10}, {"val": 4}, {"val": 10}, {"val": 12}, {"val": 5}, {"val": 6}, {"val": 2}, {"val": 7}, {"val": 9}, {"val": 4}, {"val": 5}, {"val": 9}, {"val": 2}, {"val": 15}, {"val": 11}, {"val": 4}, {"val": 6}, {"val": 7}, {"val": 4}, {"val": 7}, {"val": 16}, {"val": 13}, {"val": 7}, {"val": 6}, {"val": 5}, {"val": 10}, {"val": 4}, {"val": 5}, {"val": 8}, {"val": 5}, {"val": 5}, {"val": 4}, {"val": 6}, {"val": 8}, {"val": 6}, {"val": 4}, {"val": 16}, {"val": 5}, {"val": 6}, {"val": 7}, {"val": 5}, {"val": 12}, {"val": 10}, {"val": 4}, {"val": 4}, {"val": 7}, {"val": 8}, {"val": 2}, {"val": 4}, {"val": 4}, {"val": 7}, {"val": 7}, {"val": 5}, {"val": 5}, {"val": 7}, {"val": 12}, {"val": 5}, {"val": 5}, {"val": 6}, {"val": 7}, {"val": 7}, {"val": 10}, {"val": 6}, {"val": 6}, {"val": 2}, {"val": 14}, {"val": 14}, {"val": 6}, {"val": 6}, {"val": 3}, {"val": 3}, {"val": 8}, {"val": 4}, {"val": 6}, {"val": 9}, {"val": 8}, {"val": 12}, {"val": 8}, {"val": 5}, {"val": 4}, {"val": 6}, {"val": 11}, {"val": 5}, {"val": 7}, {"val": 5}, {"val": 4}, {"val": 4}, {"val": 9}, {"val": 9}, {"val": 9}, {"val": 5}, {"val": 8}, {"val": 11}, {"val": 9}, {"val": 7}, {"val": 9}, {"val": 6}, {"val": 20}, {"val": 8}, {"val": 14}, {"val": 4}, {"val": 8}, {"val": 6}, {"val": 5}, {"val": 11}, {"val": 5}, {"val": 5}, {"val": 9}, {"val": 8}, {"val": 4}, {"val": 10}, {"val": 6}, {"val": 5}, {"val": 7}, {"val": 14}, {"val": 9}, {"val": 8}, {"val": 4}, {"val": 4}, {"val": 14}, {"val": 8}, {"val": 4}, {"val": 3}, {"val": 11}, {"val": 3}, {"val": 10}, {"val": 6}, {"val": 7}, {"val": 6}, {"val": 5}, {"val": 5}, {"val": 4}, {"val": 5}, {"val": 10}, {"val": 7}, {"val": 6}, {"val": 12}, {"val": 4}, {"val": 8}, {"val": 6}, {"val": 5}, {"val": 10}, {"val": 24}, {"val": 4}, {"val": 4}, {"val": 4}, {"val": 9}, {"val": 12}, {"val": 4}, {"val": 5}, {"val": 4}, {"val": 7}, {"val": 12}, {"val": 4}, {"val": 4}, {"val": 4}, {"val": 13}, {"val": 9}, {"val": 4}, {"val": 7}, {"val": 5}, {"val": 11}, {"val": 14}, {"val": 9}, {"val": 8}, {"val": 10}, {"val": 5}, {"val": 3}, {"val": 10}, {"val": 7}, {"val": 3}, {"val": 15}, {"val": 21}, {"val": 11}, {"val": 6}, {"val": 6}, {"val": 16}, {"val": 8}, {"val": 10}, {"val": 6}, {"val": 9}, {"val": 5}, {"val": 4}, {"val": 11}, {"val": 7}, {"val": 3}, {"val": 12}, {"val": 7}, {"val": 13}, {"val": 18}, {"val": 8}, {"val": 4}, {"val": 4}, {"val": 8}, {"val": 4}, {"val": 22}, {"val": 16}, {"val": 7}, {"val": 4}, {"val": 4}, {"val": 8}, {"val": 10}, {"val": 5}, {"val": 8}, {"val": 6}, {"val": 5}, {"val": 4}, {"val": 7}, {"val": 3}, {"val": 3}, {"val": 9}, {"val": 11}, {"val": 4}, {"val": 9}, {"val": 4}, {"val": 15}, {"val": 8}, {"val": 11}, {"val": 4}, {"val": 7}, {"val": 7}, {"val": 21}, {"val": 7}, {"val": 3}, {"val": 8}, {"val": 5}, {"val": 3}, {"val": 10}, {"val": 5}, {"val": 6}, {"val": 7}, {"val": 5}, {"val": 12}, {"val": 5}, {"val": 9}, {"val": 14}, {"val": 6}, {"val": 11}, {"val": 5}, {"val": 7}, {"val": 10}, {"val": 9}, {"val": 4}, {"val": 7}, {"val": 6}, {"val": 4}, {"val": 3}, {"val": 4}, {"val": 7}, {"val": 3}, {"val": 5}, {"val": 4}, {"val": 5}, {"val": 17}, {"val": 6}, {"val": 3}, {"val": 6}, {"val": 4}, {"val": 5}, {"val": 10}, {"val": 4}, {"val": 4}, {"val": 3}, {"val": 7}, {"val": 8}, {"val": 3}, {"val": 5}, {"val": 7}, {"val": 10}, {"val": 4}, {"val": 4}, {"val": 10}, {"val": 5}, {"val": 5}, {"val": 6}, {"val": 6}, {"val": 10}, {"val": 6}, {"val": 6}, {"val": 6}, {"val": 7}, {"val": 4}, {"val": 16}, {"val": 5}, {"val": 16}, {"val": 14}, {"val": 8}, {"val": 4}, {"val": 4}, {"val": 4}, {"val": 10}, {"val": 10}, {"val": 7}, {"val": 6}, {"val": 5}, {"val": 2}, {"val": 4}, {"val": 5}, {"val": 15}, {"val": 4}, {"val": 3}, {"val": 3}, {"val": 5}, {"val": 7}, {"val": 9}, {"val": 3}, {"val": 7}, {"val": 12}, {"val": 13}, {"val": 5}, {"val": 4}, {"val": 3}, {"val": 3}, {"val": 3}, {"val": 12}, {"val": 6}, {"val": 5}, {"val": 6}, {"val": 7}, {"val": 7}, {"val": 11}, {"val": 9}, {"val": 6}, {"val": 15}, {"val": 8}, {"val": 4}, {"val": 7}, {"val": 14}, {"val": 10}, {"val": 7}, {"val": 8}, {"val": 8}, {"val": 16}, {"val": 19}, {"val": 4}, {"val": 4}, {"val": 11}, {"val": 10}, {"val": 12}, {"val": 5}, {"val": 4}, {"val": 9}, {"val": 4}, {"val": 8}, {"val": 7}, {"val": 3}, {"val": 12}, {"val": 6}, {"val": 5}, {"val": 4}, {"val": 18}, {"val": 23}, {"val": 4}, {"val": 3}, {"val": 3}, {"val": 5}, {"val": 12}, {"val": 5}, {"val": 13}, {"val": 12}, {"val": 7}, {"val": 4}, {"val": 10}, {"val": 13}, {"val": 4}, {"val": 5}, {"val": 18}, {"val": 5}, {"val": 8}, {"val": 4}, {"val": 6}, {"val": 9}, {"val": 11}, {"val": 7}, {"val": 5}, {"val": 6}, {"val": 6}, {"val": 11}, {"val": 3}, {"val": 10}, {"val": 3}, {"val": 5}, {"val": 9}, {"val": 10}, {"val": 3}, {"val": 13}, {"val": 5}, {"val": 6}, {"val": 7}, {"val": 5}, {"val": 5}, {"val": 4}, {"val": 16}, {"val": 3}, {"val": 6}, {"val": 3}, {"val": 5}, {"val": 4}, {"val": 3}, {"val": 7}, {"val": 4}, {"val": 9}, {"val": 8}, {"val": 7}, {"val": 6}, {"val": 4}, {"val": 13}, {"val": 15}, {"val": 13}, {"val": 5}, {"val": 4}, {"val": 6}, {"val": 6}, {"val": 10}, {"val": 12}, {"val": 5}, {"val": 6}, {"val": 11}, {"val": 7}, {"val": 4}, {"val": 12}, {"val": 3}, {"val": 5}, {"val": 7}, {"val": 11}, {"val": 5}, {"val": 8}, {"val": 12}, {"val": 5}, {"val": 6}, {"val": 10}, {"val": 9}, {"val": 8}, {"val": 3}, {"val": 7}, {"val": 9}, {"val": 13}, {"val": 4}, {"val": 12}, {"val": 3}, {"val": 5}, {"val": 2}, {"val": 4}, {"val": 11}, {"val": 3}, {"val": 20}, {"val": 8}, {"val": 3}, {"val": 6}, {"val": 4}, {"val": 7}, {"val": 4}, {"val": 4}, {"val": 7}, {"val": 3}, {"val": 13}, {"val": 5}, {"val": 4}, {"val": 7}, {"val": 11}, {"val": 5}, {"val": 4}, {"val": 6}, {"val": 5}, {"val": 8}, {"val": 3}, {"val": 4}, {"val": 5}, {"val": 15}, {"val": 4}, {"val": 3}, {"val": 6}, {"val": 9}, {"val": 6}, {"val": 9}, {"val": 6}, {"val": 3}, {"val": 10}, {"val": 12}, {"val": 5}, {"val": 5}, {"val": 5}, {"val": 5}, {"val": 4}, {"val": 10}, {"val": 5}, {"val": 10}, {"val": 6}, {"val": 9}, {"val": 5}, {"val": 12}, {"val": 5}, {"val": 10}, {"val": 5}, {"val": 6}, {"val": 17}, {"val": 6}, {"val": 7}, {"val": 11}, {"val": 19}, {"val": 3}, {"val": 5}, {"val": 8}, {"val": 7}, {"val": 6}, {"val": 10}, {"val": 13}, {"val": 7}, {"val": 3}, {"val": 7}, {"val": 5}, {"val": 12}, {"val": 4}, {"val": 7}, {"val": 11}, {"val": 9}, {"val": 7}, {"val": 4}, {"val": 14}, {"val": 3}, {"val": 6}, {"val": 7}, {"val": 13}, {"val": 7}, {"val": 4}, {"val": 5}, {"val": 15}, {"val": 9}, {"val": 3}, {"val": 5}, {"val": 3}, {"val": 7}, {"val": 9}, {"val": 15}, {"val": 8}, {"val": 3}, {"val": 7}, {"val": 4}, {"val": 13}, {"val": 2}, {"val": 4}, {"val": 3}, {"val": 5}, {"val": 6}, {"val": 7}, {"val": 8}, {"val": 3}, {"val": 14}, {"val": 9}, {"val": 17}, {"val": 9}, {"val": 5}, {"val": 19}, {"val": 4}, {"val": 6}, {"val": 8}, {"val": 12}, {"val": 10}, {"val": 6}, {"val": 4}, {"val": 5}, {"val": 5}, {"val": 10}, {"val": 18}, {"val": 11}, {"val": 5}, {"val": 5}, {"val": 6}, {"val": 12}, {"val": 5}, {"val": 6}, {"val": 17}, {"val": 8}, {"val": 2}, {"val": 11}, {"val": 7}, {"val": 12}, {"val": 9}, {"val": 8}, {"val": 5}, {"val": 5}, {"val": 4}, {"val": 4}, {"val": 12}, {"val": 5}, {"val": 15}, {"val": 11}, {"val": 5}, {"val": 7}, {"val": 4}, {"val": 6}, {"val": 1}, {"val": 6}, {"val": 7}, {"val": 6}, {"val": 4}, {"val": 4}, {"val": 7}, {"val": 5}, {"val": 9}, {"val": 5}, {"val": 5}, {"val": 5}, {"val": 3}, {"val": 2}, {"val": 3}, {"val": 5}, {"val": 6}, {"val": 9}, {"val": 9}, {"val": 8}, {"val": 7}, {"val": 9}, {"val": 7}, {"val": 3}, {"val": 8}, {"val": 12}, {"val": 12}, {"val": 12}, {"val": 4}, {"val": 3}, {"val": 3}, {"val": 2}, {"val": 5}, {"val": 16}, {"val": 10}, {"val": 7}, {"val": 9}, {"val": 5}, {"val": 7}, {"val": 5}, {"val": 20}, {"val": 8}, {"val": 14}, {"val": 5}, {"val": 4}, {"val": 4}, {"val": 8}, {"val": 3}, {"val": 4}, {"val": 5}, {"val": 9}, {"val": 15}, {"val": 7}, {"val": 12}, {"val": 2}, {"val": 7}, {"val": 7}, {"val": 3}, {"val": 3}, {"val": 5}, {"val": 4}, {"val": 11}, {"val": 11}, {"val": 10}, {"val": 24}, {"val": 4}, {"val": 8}, {"val": 6}, {"val": 15}, {"val": 10}, {"val": 10}, {"val": 9}, {"val": 6}, {"val": 4}, {"val": 6}, {"val": 4}, {"val": 17}, {"val": 9}, {"val": 5}, {"val": 4}, {"val": 9}, {"val": 5}, {"val": 5}, {"val": 11}, {"val": 4}, {"val": 5}, {"val": 5}, {"val": 8}, {"val": 5}, {"val": 8}, {"val": 8}, {"val": 9}, {"val": 7}, {"val": 5}, {"val": 9}, {"val": 4}, {"val": 12}, {"val": 4}, {"val": 7}, {"val": 3}, {"val": 9}, {"val": 4}, {"val": 4}, {"val": 14}, {"val": 9}, {"val": 6}, {"val": 6}, {"val": 15}, {"val": 7}, {"val": 6}, {"val": 11}, {"val": 13}, {"val": 5}, {"val": 7}, {"val": 7}, {"val": 4}, {"val": 4}, {"val": 7}, {"val": 9}, {"val": 9}, {"val": 10}, {"val": 7}, {"val": 7}, {"val": 17}, {"val": 4}, {"val": 8}, {"val": 3}, {"val": 3}, {"val": 15}, {"val": 7}, {"val": 5}, {"val": 6}, {"val": 7}, {"val": 7}, {"val": 7}, {"val": 6}, {"val": 9}, {"val": 6}, {"val": 16}, {"val": 5}, {"val": 5}, {"val": 5}, {"val": 10}, {"val": 5}, {"val": 5}, {"val": 4}, {"val": 4}, {"val": 19}, {"val": 9}, {"val": 10}, {"val": 12}, {"val": 3}, {"val": 14}, {"val": 4}, {"val": 6}, {"val": 8}, {"val": 6}, {"val": 8}, {"val": 9}, {"val": 8}, {"val": 11}, {"val": 11}, {"val": 4}, {"val": 9}, {"val": 4}, {"val": 5}, {"val": 4}, {"val": 7}, {"val": 4}, {"val": 9}, {"val": 14}, {"val": 7}, {"val": 2}, {"val": 2}, {"val": 10}, {"val": 7}, {"val": 4}, {"val": 2}, {"val": 5}, {"val": 8}, {"val": 2}, {"val": 4}, {"val": 4}, {"val": 17}, {"val": 4}, {"val": 14}, {"val": 3}, {"val": 5}, {"val": 6}, {"val": 5}, {"val": 4}, {"val": 6}, {"val": 2}, {"val": 12}, {"val": 7}, {"val": 2}, {"val": 6}, {"val": 5}, {"val": 3}, {"val": 4}, {"val": 4}, {"val": 4}, {"val": 5}, {"val": 12}, {"val": 9}, {"val": 7}, {"val": 3}, {"val": 3}, {"val": 3}, {"val": 4}, {"val": 2}, {"val": 6}, {"val": 11}, {"val": 9}, {"val": 6}, {"val": 5}, {"val": 11}, {"val": 5}, {"val": 5}, {"val": 9}, {"val": 2}, {"val": 5}, {"val": 7}, {"val": 8}, {"val": 7}, {"val": 9}, {"val": 6}, {"val": 3}, {"val": 4}, {"val": 8}, {"val": 7}, {"val": 21}, {"val": 4}, {"val": 3}, {"val": 13}, {"val": 6}, {"val": 4}, {"val": 8}, {"val": 4}, {"val": 4}, {"val": 6}, {"val": 5}, {"val": 6}, {"val": 7}, {"val": 8}, {"val": 4}, {"val": 5}, {"val": 4}, {"val": 7}, {"val": 4}, {"val": 9}, {"val": 6}, {"val": 11}, {"val": 12}, {"val": 4}, {"val": 4}, {"val": 26}, {"val": 4}, {"val": 6}, {"val": 4}, {"val": 4}, {"val": 5}, {"val": 5}, {"val": 5}, {"val": 13}, {"val": 9}, {"val": 9}, {"val": 7}, {"val": 5}, {"val": 4}, {"val": 5}, {"val": 12}, {"val": 7}, {"val": 3}, {"val": 5}, {"val": 7}, {"val": 4}, {"val": 10}, {"val": 4}, {"val": 4}, {"val": 8}, {"val": 7}, {"val": 8}, {"val": 6}, {"val": 4}, {"val": 4}, {"val": 6}, {"val": 5}, {"val": 11}, {"val": 9}, {"val": 7}, {"val": 7}, {"val": 9}, {"val": 4}, {"val": 5}, {"val": 4}, {"val": 5}, {"val": 5}, {"val": 5}, {"val": 4}, {"val": 6}, {"val": 6}, {"val": 11}, {"val": 5}, {"val": 4}, {"val": 9}, {"val": 6}, {"val": 9}, {"val": 3}, {"val": 6}, {"val": 9}, {"val": 14}, {"val": 7}, {"val": 5}, {"val": 8}, {"val": 6}, {"val": 8}, {"val": 5}, {"val": 9}, {"val": 10}, {"val": 4}, {"val": 5}, {"val": 9}, {"val": 6}, {"val": 7}, {"val": 13}, {"val": 7}, {"val": 4}, {"val": 7}, {"val": 4}, {"val": 4}, {"val": 6}, {"val": 10}, {"val": 6}, {"val": 4}, {"val": 11}, {"val": 5}, {"val": 8}, {"val": 5}, {"val": 8}, {"val": 7}, {"val": 6}, {"val": 7}, {"val": 8}, {"val": 4}, {"val": 4}, {"val": 4}, {"val": 21}, {"val": 4}, {"val": 3}, {"val": 4}, {"val": 3}, {"val": 5}, {"val": 6}, {"val": 11}, {"val": 4}, {"val": 9}, {"val": 3}, {"val": 5}, {"val": 10}, {"val": 4}, {"val": 5}, {"val": 7}, {"val": 10}, {"val": 4}, {"val": 6}, {"val": 4}, {"val": 4}, {"val": 8}, {"val": 11}, {"val": 11}, {"val": 7}, {"val": 5}, {"val": 6}, {"val": 7}, {"val": 4}, {"val": 6}, {"val": 3}, {"val": 11}, {"val": 4}, {"val": 4}, {"val": 3}, {"val": 4}, {"val": 9}, {"val": 7}, {"val": 6}, {"val": 6}, {"val": 5}, {"val": 7}, {"val": 3}, {"val": 8}, {"val": 8}, {"val": 12}, {"val": 7}, {"val": 3}, {"val": 27}, {"val": 4}, {"val": 5}, {"val": 2}, {"val": 4}, {"val": 12}, {"val": 5}, {"val": 17}, {"val": 5}, {"val": 14}, {"val": 3}, {"val": 7}, {"val": 11}, {"val": 7}, {"val": 6}, {"val": 12}, {"val": 6}, {"val": 3}, {"val": 11}, {"val": 10}, {"val": 4}, {"val": 5}, {"val": 7}, {"val": 5}, {"val": 11}, {"val": 6}, {"val": 6}, {"val": 4}, {"val": 4}, {"val": 14}, {"val": 4}, {"val": 6}, {"val": 5}, {"val": 5}, {"val": 6}, {"val": 7}, {"val": 7}, {"val": 7}, {"val": 5}, {"val": 7}, {"val": 13}, {"val": 3}, {"val": 17}, {"val": 5}, {"val": 13}, {"val": 5}, {"val": 19}, {"val": 14}, {"val": 10}, {"val": 6}, {"val": 9}, {"val": 4}, {"val": 5}, {"val": 4}, {"val": 7}, {"val": 5}, {"val": 5}, {"val": 5}, {"val": 4}, {"val": 10}, {"val": 4}, {"val": 4}, {"val": 6}, {"val": 5}, {"val": 7}, {"val": 6}, {"val": 5}, {"val": 4}, {"val": 10}, {"val": 6}, {"val": 4}, {"val": 12}, {"val": 18}, {"val": 7}, {"val": 5}, {"val": 5}, {"val": 10}, {"val": 6}, {"val": 5}, {"val": 15}, {"val": 19}, {"val": 11}, {"val": 8}, {"val": 10}, {"val": 10}, {"val": 3}, {"val": 3}, {"val": 10}, {"val": 8}, {"val": 9}, {"val": 6}, {"val": 4}, {"val": 12}, {"val": 5}, {"val": 18}, {"val": 7}, {"val": 5}, {"val": 8}, {"val": 8}, {"val": 4}, {"val": 5}, {"val": 4}, {"val": 5}, {"val": 4}, {"val": 8}, {"val": 6}, {"val": 12}, {"val": 7}, {"val": 6}, {"val": 7}, {"val": 6}, {"val": 7}, {"val": 6}, {"val": 10}, {"val": 8}, {"val": 3}, {"val": 8}, {"val": 8}, {"val": 3}, {"val": 5}, {"val": 6}, {"val": 8}, {"val": 7}, {"val": 3}, {"val": 3}, {"val": 3}, {"val": 11}, {"val": 7}, {"val": 19}, {"val": 4}, {"val": 4}, {"val": 10}, {"val": 6}, {"val": 4}, {"val": 5}, {"val": 3}, {"val": 12}, {"val": 7}, {"val": 9}, {"val": 8}, {"val": 5}, {"val": 3}, {"val": 4}, {"val": 4}, {"val": 3}, {"val": 6}, {"val": 4}, {"val": 5}, {"val": 7}, {"val": 7}, {"val": 5}, {"val": 4}, {"val": 4}, {"val": 8}, {"val": 5}, {"val": 7}, {"val": 5}, {"val": 3}, {"val": 6}, {"val": 2}, {"val": 3}, {"val": 2}, {"val": 3}, {"val": 6}, {"val": 7}, {"val": 2}, {"val": 2}, {"val": 5}, {"val": 6}, {"val": 3}, {"val": 4}, {"val": 9}, {"val": 7}, {"val": 2}, {"val": 2}, {"val": 2}, {"val": 3}, {"val": 5}, {"val": 5}, {"val": 4}, {"val": 6}, {"val": 8}, {"val": 4}, {"val": 5}, {"val": 3}, {"val": 15}, {"val": 1}, {"val": 6}, {"val": 4}, {"val": 7}, {"val": 5}, {"val": 10}, {"val": 5}, {"val": 3}, {"val": 9}, {"val": 2}, {"val": 4}, {"val": 7}, {"val": 7}, {"val": 9}, {"val": 6}, {"val": 4}, {"val": 11}, {"val": 6}, {"val": 4}, {"val": 8}, {"val": 24}, {"val": 4}, {"val": 5}, {"val": 4}, {"val": 3}, {"val": 10}, {"val": 11}, {"val": 3}, {"val": 9}, {"val": 7}, {"val": 6}, {"val": 11}, {"val": 11}, {"val": 6}, {"val": 5}, {"val": 4}, {"val": 4}, {"val": 9}, {"val": 6}, {"val": 9}, {"val": 9}, {"val": 9}, {"val": 7}, {"val": 3}, {"val": 4}, {"val": 5}, {"val": 2}, {"val": 4}, {"val": 4}, {"val": 7}, {"val": 12}, {"val": 3}, {"val": 8}, {"val": 5}, {"val": 4}, {"val": 1}, {"val": 4}, {"val": 4}, {"val": 4}, {"val": 10}, {"val": 7}, {"val": 3}, {"val": 8}, {"val": 9}, {"val": 4}, {"val": 6}, {"val": 11}, {"val": 5}, {"val": 8}, {"val": 3}, {"val": 6}, {"val": 11}, {"val": 2}, {"val": 5}, {"val": 3}, {"val": 6}, {"val": 6}, {"val": 9}, {"val": 5}, {"val": 3}, {"val": 5}, {"val": 17}, {"val": 2}, {"val": 7}, {"val": 4}, {"val": 11}, {"val": 9}, {"val": 9}, {"val": 5}, {"val": 6}, {"val": 7}, {"val": 7}, {"val": 10}, {"val": 4}, {"val": 4}, {"val": 5}, {"val": 8}, {"val": 4}, {"val": 2}, {"val": 11}, {"val": 5}, {"val": 4}, {"val": 3}, {"val": 3}, {"val": 5}, {"val": 9}, {"val": 7}, {"val": 4}, {"val": 12}, {"val": 4}, {"val": 2}, {"val": 5}, {"val": 5}, {"val": 7}, {"val": 9}, {"val": 5}, {"val": 4}, {"val": 3}, {"val": 4}, {"val": 10}, {"val": 3}, {"val": 3}, {"val": 2}, {"val": 4}, {"val": 7}, {"val": 10}, {"val": 4}, {"val": 5}, {"val": 8}, {"val": 4}, {"val": 5}, {"val": 6}, {"val": 6}, {"val": 5}, {"val": 6}, {"val": 3}, {"val": 7}, {"val": 8}, {"val": 3}, {"val": 6}, {"val": 4}, {"val": 3}, {"val": 3}, {"val": 4}, {"val": 5}, {"val": 8}, {"val": 2}, {"val": 7}, {"val": 3}, {"val": 4}, {"val": 7}, {"val": 5}, {"val": 2}, {"val": 3}, {"val": 4}, {"val": 6}, {"val": 6}, {"val": 3}, {"val": 5}, {"val": 2}, {"val": 3}, {"val": 4}, {"val": 8}, {"val": 4}, {"val": 6}, {"val": 6}, {"val": 7}, {"val": 2}, {"val": 6}, {"val": 5}, {"val": 6}, {"val": 3}, {"val": 4}, {"val": 7}, {"val": 5}, {"val": 5}, {"val": 5}, {"val": 4}, {"val": 3}, {"val": 4}, {"val": 4}, {"val": 3}, {"val": 4}, {"val": 3}, {"val": 5}, {"val": 6}, {"val": 5}, {"val": 3}, {"val": 3}, {"val": 2}, {"val": 7}, {"val": 3}, {"val": 5}, {"val": 4}, {"val": 2}, {"val": 4}, {"val": 4}, {"val": 6}, {"val": 3}, {"val": 4}, {"val": 3}, {"val": 4}, {"val": 4}, {"val": 3}, {"val": 3}, {"val": 2}, {"val": 3}, {"val": 2}, {"val": 3}, {"val": 4}, {"val": 7}, {"val": 4}, {"val": 3}, {"val": 4}, {"val": 4}, {"val": 6}, {"val": 6}, {"val": 8}, {"val": 4}, {"val": 7}, {"val": 1}, {"val": 8}, {"val": 3}, {"val": 4}, {"val": 4}, {"val": 6}, {"val": 4}, {"val": 6}, {"val": 6}, {"val": 4}, {"val": 4}, {"val": 4}, {"val": 6}, {"val": 3}, {"val": 4}, {"val": 4}, {"val": 3}, {"val": 11}, {"val": 10}, {"val": 3}, {"val": 4}, {"val": 4}, {"val": 4}, {"val": 6}, {"val": 3}, {"val": 2}, {"val": 4}, {"val": 3}, {"val": 4}, {"val": 3}, {"val": 6}, {"val": 4}, {"val": 4}, {"val": 4}, {"val": 4}, {"val": 3}, {"val": 5}, {"val": 3}, {"val": 2}, {"val": 4}, {"val": 12}, {"val": 6}, {"val": 4}, {"val": 2}, {"val": 5}, {"val": 9}, {"val": 4}, {"val": 6}, {"val": 3}, {"val": 5}, {"val": 3}, {"val": 4}, {"val": 6}, {"val": 4}, {"val": 4}, {"val": 4}, {"val": 4}, {"val": 5}, {"val": 5}, {"val": 6}, {"val": 8}, {"val": 3}, {"val": 6}, {"val": 4}, {"val": 6}, {"val": 10}, {"val": 3}, {"val": 3}, {"val": 5}, {"val": 6}, {"val": 6}, {"val": 3}, {"val": 3}, {"val": 4}, {"val": 4}, {"val": 6}, {"val": 6}, {"val": 3}, {"val": 5}, {"val": 5}, {"val": 7}, {"val": 5}, {"val": 4}, {"val": 7}, {"val": 5}, {"val": 4}, {"val": 4}, {"val": 6}, {"val": 6}, {"val": 4}, {"val": 7}, {"val": 4}, {"val": 4}, {"val": 4}, {"val": 4}, {"val": 7}, {"val": 4}, {"val": 6}, {"val": 7}, {"val": 5}, {"val": 5}, {"val": 3}, {"val": 4}, {"val": 4}, {"val": 4}, {"val": 8}, {"val": 7}, {"val": 7}, {"val": 4}, {"val": 4}, {"val": 8}, {"val": 5}, {"val": 5}, {"val": 5}, {"val": 3}, {"val": 9}, {"val": 9}, {"val": 6}, {"val": 4}, {"val": 3}, {"val": 5}, {"val": 5}, {"val": 4}, {"val": 5}, {"val": 5}, {"val": 7}, {"val": 5}, {"val": 15}, {"val": 4}, {"val": 6}, {"val": 2}, {"val": 5}, {"val": 9}, {"val": 6}, {"val": 7}, {"val": 6}, {"val": 12}, {"val": 18}, {"val": 5}, {"val": 11}, {"val": 9}, {"val": 10}, {"val": 13}, {"val": 10}, {"val": 4}, {"val": 7}, {"val": 5}, {"val": 4}, {"val": 10}, {"val": 3}, {"val": 3}, {"val": 16}, {"val": 6}, {"val": 4}, {"val": 4}, {"val": 5}, {"val": 5}, {"val": 10}, {"val": 8}, {"val": 8}, {"val": 7}, {"val": 11}, {"val": 8}, {"val": 13}, {"val": 5}, {"val": 6}, {"val": 6}, {"val": 18}, {"val": 4}, {"val": 7}, {"val": 12}, {"val": 4}, {"val": 6}, {"val": 4}, {"val": 6}, {"val": 3}, {"val": 6}, {"val": 11}, {"val": 3}, {"val": 8}, {"val": 5}, {"val": 5}, {"val": 4}, {"val": 3}, {"val": 4}, {"val": 3}, {"val": 6}, {"val": 2}, {"val": 3}, {"val": 2}, {"val": 2}, {"val": 6}, {"val": 4}, {"val": 4}, {"val": 4}, {"val": 5}, {"val": 4}, {"val": 8}, {"val": 5}, {"val": 5}, {"val": 5}, {"val": 7}, {"val": 4}, {"val": 4}, {"val": 4}, {"val": 4}, {"val": 4}, {"val": 6}, {"val": 13}, {"val": 5}, {"val": 7}, {"val": 5}, {"val": 5}, {"val": 3}, {"val": 9}, {"val": 6}, {"val": 7}, {"val": 6}, {"val": 7}, {"val": 4}, {"val": 4}, {"val": 4}, {"val": 2}, {"val": 1}, {"val": 5}, {"val": 5}, {"val": 1}, {"val": 4}, {"val": 2}, {"val": 2}, {"val": 6}, {"val": 4}, {"val": 4}, {"val": 2}, {"val": 2}, {"val": 3}, {"val": 3}, {"val": 2}, {"val": 2}, {"val": 3}, {"val": 2}, {"val": 7}, {"val": 5}, {"val": 4}, {"val": 8}, {"val": 2}, {"val": 2}, {"val": 7}, {"val": 3}, {"val": 4}, {"val": 5}, {"val": 4}, {"val": 4}, {"val": 5}, {"val": 5}, {"val": 5}, {"val": 2}, {"val": 12}, {"val": 4}, {"val": 7}, {"val": 5}, {"val": 7}, {"val": 6}, {"val": 6}, {"val": 10}, {"val": 5}, {"val": 6}, {"val": 5}, {"val": 4}, {"val": 5}, {"val": 3}, {"val": 3}, {"val": 4}, {"val": 4}, {"val": 7}, {"val": 6}, {"val": 3}, {"val": 6}, {"val": 12}, {"val": 6}, {"val": 4}, {"val": 2}, {"val": 5}, {"val": 2}, {"val": 5}, {"val": 5}, {"val": 3}, {"val": 3}, {"val": 9}, {"val": 5}, {"val": 6}, {"val": 3}, {"val": 4}, {"val": 13}, {"val": 8}, {"val": 8}, {"val": 4}, {"val": 4}, {"val": 4}, {"val": 7}, {"val": 4}, {"val": 3}, {"val": 4}, {"val": 4}, {"val": 9}, {"val": 4}, {"val": 4}, {"val": 5}, {"val": 6}, {"val": 3}, {"val": 4}, {"val": 4}, {"val": 4}, {"val": 3}, {"val": 5}, {"val": 5}, {"val": 7}, {"val": 6}, {"val": 3}, {"val": 5}, {"val": 5}, {"val": 4}, {"val": 5}, {"val": 4}, {"val": 10}, {"val": 4}, {"val": 3}, {"val": 6}, {"val": 5}, {"val": 13}, {"val": 5}, {"val": 6}, {"val": 7}, {"val": 3}, {"val": 5}, {"val": 5}, {"val": 4}, {"val": 5}, {"val": 3}, {"val": 1}, {"val": 5}, {"val": 7}, {"val": 5}, {"val": 6}, {"val": 4}, {"val": 4}, {"val": 4}, {"val": 3}, {"val": 8}, {"val": 10}, {"val": 5}, {"val": 5}, {"val": 10}, {"val": 4}, {"val": 2}, {"val": 3}, {"val": 5}, {"val": 6}, {"val": 8}, {"val": 3}, {"val": 3}, {"val": 4}, {"val": 6}, {"val": 3}, {"val": 4}, {"val": 6}, {"val": 4}, {"val": 4}, {"val": 6}, {"val": 5}, {"val": 3}, {"val": 6}, {"val": 7}, {"val": 6}, {"val": 5}, {"val": 4}, {"val": 5}, {"val": 4}, {"val": 3}, {"val": 4}, {"val": 4}, {"val": 3}, {"val": 1}, {"val": 4}, {"val": 4}, {"val": 10}, {"val": 10}, {"val": 7}, {"val": 5}, {"val": 7}, {"val": 3}, {"val": 3}, {"val": 4}, {"val": 5}, {"val": 7}, {"val": 4}, {"val": 6}, {"val": 9}, {"val": 7}, {"val": 4}, {"val": 4}, {"val": 6}, {"val": 1}, {"val": 9}, {"val": 7}, {"val": 5}, {"val": 8}, {"val": 3}, {"val": 3}, {"val": 1}, {"val": 1}, {"val": 5}, {"val": 5}, {"val": 6}, {"val": 7}, {"val": 7}, {"val": 4}, {"val": 3}, {"val": 3}, {"val": 4}, {"val": 4}, {"val": 4}, {"val": 1}, {"val": 4}, {"val": 4}, {"val": 5}, {"val": 5}, {"val": 9}, {"val": 1}, {"val": 4}, {"val": 4}, {"val": 4}, {"val": 6}, {"val": 5}, {"val": 14}, {"val": 8}, {"val": 9}, {"val": 6}, {"val": 6}, {"val": 5}, {"val": 3}, {"val": 5}, {"val": 4}, {"val": 3}, {"val": 11}, {"val": 12}, {"val": 7}, {"val": 7}, {"val": 9}, {"val": 5}, {"val": 4}, {"val": 3}, {"val": 9}, {"val": 13}, {"val": 9}, {"val": 4}, {"val": 3}, {"val": 4}, {"val": 4}, {"val": 8}, {"val": 4}, {"val": 4}, {"val": 3}, {"val": 5}, {"val": 4}, {"val": 4}, {"val": 6}, {"val": 4}, {"val": 3}, {"val": 4}, {"val": 7}, {"val": 5}, {"val": 3}, {"val": 8}, {"val": 8}, {"val": 4}, {"val": 8}, {"val": 6}, {"val": 18}, {"val": 7}, {"val": 9}, {"val": 6}, {"val": 10}, {"val": 6}, {"val": 5}, {"val": 5}, {"val": 3}, {"val": 6}, {"val": 5}, {"val": 4}, {"val": 5}, {"val": 4}, {"val": 2}, {"val": 4}, {"val": 5}, {"val": 4}, {"val": 5}, {"val": 3}, {"val": 5}, {"val": 5}, {"val": 10}, {"val": 6}, {"val": 3}, {"val": 4}, {"val": 7}, {"val": 4}, {"val": 4}, {"val": 4}, {"val": 4}, {"val": 7}, {"val": 8}, {"val": 3}, {"val": 4}, {"val": 5}, {"val": 3}, {"val": 7}, {"val": 4}, {"val": 7}, {"val": 5}, {"val": 5}, {"val": 4}, {"val": 7}, {"val": 7}, {"val": 5}, {"val": 8}, {"val": 4}, {"val": 4}, {"val": 10}, {"val": 6}, {"val": 10}, {"val": 2}, {"val": 4}, {"val": 5}, {"val": 5}, {"val": 5}, {"val": 3}, {"val": 3}, {"val": 4}, {"val": 10}, {"val": 4}, {"val": 4}, {"val": 4}, {"val": 4}, {"val": 9}, {"val": 5}, {"val": 4}, {"val": 5}, {"val": 5}, {"val": 3}, {"val": 3}, {"val": 7}, {"val": 7}, {"val": 5}, {"val": 4}, {"val": 7}, {"val": 4}, {"val": 4}, {"val": 2}, {"val": 4}, {"val": 7}, {"val": 4}, {"val": 10}, {"val": 4}, {"val": 6}, {"val": 7}, {"val": 6}, {"val": 3}, {"val": 6}, {"val": 3}, {"val": 4}, {"val": 4}, {"val": 3}, {"val": 5}, {"val": 3}, {"val": 2}, {"val": 7}, {"val": 4}, {"val": 2}, {"val": 5}, {"val": 4}, {"val": 7}, {"val": 4}, {"val": 6}, {"val": 4}, {"val": 8}, {"val": 6}, {"val": 4}, {"val": 5}, {"val": 11}, {"val": 4}, {"val": 6}, {"val": 4}, {"val": 5}, {"val": 8}, {"val": 3}, {"val": 3}, {"val": 3}, {"val": 4}, {"val": 6}, {"val": 7}, {"val": 6}, {"val": 2}, {"val": 3}, {"val": 2}, {"val": 6}, {"val": 6}, {"val": 7}, {"val": 4}, {"val": 4}, {"val": 2}, {"val": 4}, {"val": 2}, {"val": 2}, {"val": 6}, {"val": 9}, {"val": 4}, {"val": 5}, {"val": 6}, {"val": 5}, {"val": 4}, {"val": 8}, {"val": 8}, {"val": 4}, {"val": 3}, {"val": 3}, {"val": 4}, {"val": 7}, {"val": 3}, {"val": 5}, {"val": 5}, {"val": 5}, {"val": 6}, {"val": 5}, {"val": 5}, {"val": 3}, {"val": 8}, {"val": 3}, {"val": 3}, {"val": 3}, {"val": 4}, {"val": 11}, {"val": 5}, {"val": 5}, {"val": 6}, {"val": 4}, {"val": 2}, {"val": 2}, {"val": 5}, {"val": 10}, {"val": 6}, {"val": 5}, {"val": 3}, {"val": 9}, {"val": 8}, {"val": 9}, {"val": 2}, {"val": 3}, {"val": 4}, {"val": 3}, {"val": 12}, {"val": 10}, {"val": 7}, {"val": 4}, {"val": 6}, {"val": 10}, {"val": 6}, {"val": 14}, {"val": 4}, {"val": 4}, {"val": 4}, {"val": 7}, {"val": 3}, {"val": 12}, {"val": 4}, {"val": 5}, {"val": 4}, {"val": 5}, {"val": 6}, {"val": 7}, {"val": 5}, {"val": 3}, {"val": 3}, {"val": 2}, {"val": 3}, {"val": 2}, {"val": 4}, {"val": 2}, {"val": 2}, {"val": 3}, {"val": 2}, {"val": 3}, {"val": 8}, {"val": 2}, {"val": 4}, {"val": 2}, {"val": 2}, {"val": 6}, {"val": 1}, {"val": 1}, {"val": 1}, {"val": 3}, {"val": 1}, {"val": 3}, {"val": 1}, {"val": 3}, {"val": 8}, {"val": 9}, {"val": 4}, {"val": 5}, {"val": 3}, {"val": 10}, {"val": 4}, {"val": 9}, {"val": 3}, {"val": 3}, {"val": 13}, {"val": 4}, {"val": 4}, {"val": 7}, {"val": 11}, {"val": 4}, {"val": 4}, {"val": 4}, {"val": 4}, {"val": 15}, {"val": 2}, {"val": 2}, {"val": 4}, {"val": 3}, {"val": 4}, {"val": 6}, {"val": 7}, {"val": 7}, {"val": 9}, {"val": 5}, {"val": 4}, {"val": 4}, {"val": 4}, {"val": 4}, {"val": 4}, {"val": 4}, {"val": 2}, {"val": 5}, {"val": 5}, {"val": 9}, {"val": 8}, {"val": 7}, {"val": 5}, {"val": 7}, {"val": 5}, {"val": 4}, {"val": 3}, {"val": 4}, {"val": 4}, {"val": 7}, {"val": 4}, {"val": 11}, {"val": 4}, {"val": 6}, {"val": 5}, {"val": 4}, {"val": 6}, {"val": 5}, {"val": 8}, {"val": 6}, {"val": 4}, {"val": 5}, {"val": 4}, {"val": 3}, {"val": 4}, {"val": 5}, {"val": 3}, {"val": 3}, {"val": 3}, {"val": 5}, {"val": 2}, {"val": 6}, {"val": 4}, {"val": 8}, {"val": 5}, {"val": 6}, {"val": 5}, {"val": 4}, {"val": 5}, {"val": 8}, {"val": 4}, {"val": 4}, {"val": 5}, {"val": 5}, {"val": 9}, {"val": 8}, {"val": 8}, {"val": 4}, {"val": 6}, {"val": 6}, {"val": 4}, {"val": 8}, {"val": 3}, {"val": 3}, {"val": 4}, {"val": 7}, {"val": 3}, {"val": 5}, {"val": 4}, {"val": 7}, {"val": 6}, {"val": 3}, {"val": 3}, {"val": 1}, {"val": 2}, {"val": 5}, {"val": 8}, {"val": 8}, {"val": 3}, {"val": 4}, {"val": 4}, {"val": 4}, {"val": 4}, {"val": 3}, {"val": 6}, {"val": 9}, {"val": 4}, {"val": 2}, {"val": 7}, {"val": 5}, {"val": 6}, {"val": 3}, {"val": 4}, {"val": 3}, {"val": 3}, {"val": 3}, {"val": 2}, {"val": 7}, {"val": 3}, {"val": 3}, {"val": 3}, {"val": 5}, {"val": 3}, {"val": 4}, {"val": 13}, {"val": 7}, {"val": 7}, {"val": 3}, {"val": 5}, {"val": 4}, {"val": 9}, {"val": 4}, {"val": 4}, {"val": 9}, {"val": 6}, {"val": 4}, {"val": 4}, {"val": 7}, {"val": 3}, {"val": 6}, {"val": 4}, {"val": 4}, {"val": 4}, {"val": 4}, {"val": 10}, {"val": 7}, {"val": 4}, {"val": 3}, {"val": 4}, {"val": 11}, {"val": 4}, {"val": 4}, {"val": 6}, {"val": 7}, {"val": 13}, {"val": 16}, {"val": 5}, {"val": 2}, {"val": 2}, {"val": 6}, {"val": 4}, {"val": 7}, {"val": 3}, {"val": 4}, {"val": 9}, {"val": 3}, {"val": 4}, {"val": 4}, {"val": 4}, {"val": 5}, {"val": 8}, {"val": 9}, {"val": 3}, {"val": 11}, {"val": 8}, {"val": 5}, {"val": 4}, {"val": 3}, {"val": 5}, {"val": 5}, {"val": 5}, {"val": 4}, {"val": 8}, {"val": 2}, {"val": 3}, {"val": 4}, {"val": 2}, {"val": 2}, {"val": 4}, {"val": 4}, {"val": 5}, {"val": 4}, {"val": 5}, {"val": 5}, {"val": 9}, {"val": 5}, {"val": 7}, {"val": 5}, {"val": 4}, {"val": 4}, {"val": 3}, {"val": 7}, {"val": 8}, {"val": 4}, {"val": 9}, {"val": 4}, {"val": 6}, {"val": 7}, {"val": 5}, {"val": 2}, {"val": 3}, {"val": 4}, {"val": 9}, {"val": 6}, {"val": 12}, {"val": 6}, {"val": 3}, {"val": 5}, {"val": 5}, {"val": 5}, {"val": 5}, {"val": 6}, {"val": 4}, {"val": 6}, {"val": 14}, {"val": 7}, {"val": 4}, {"val": 9}, {"val": 6}, {"val": 4}, {"val": 7}, {"val": 5}, {"val": 6}, {"val": 4}, {"val": 6}, {"val": 5}, {"val": 6}], "chord_sets": [{"x": 3.9014373716632442, "y": "Am, C, F, G"}, {"x": 2.087611225188227, "y": "C, D, Em, G"}, {"x": 1.3689253935660506, "y": "C, F, G7"}, {"x": 1.3347022587268993, "y": "Am, C, Dm, F, G"}, {"x": 1.163586584531143, "y": "C, F, G"}, {"x": 0.9240246406570842, "y": "Am, C, D, Em, G"}, {"x": 0.9240246406570842, "y": "Bb, C, Dm, F"}, {"x": 0.7529089664613279, "y": "Am, C, Em, F, G"}, {"x": 0.7186858316221766, "y": "C, F"}, {"x": 0.6502395619438741, "y": "C, D, G"}, {"x": 0.6160164271047228, "y": "A, Bm, D, G"}, {"x": 0.6160164271047228, "y": "Am, Bm, C, D, Em, G"}, {"x": 0.6160164271047228, "y": "C, G7"}, {"x": 0.5817932922655715, "y": "C, D7, G"}, {"x": 0.5817932922655715, "y": "Am, C, Dm, Em, F, G"}], "keys": [{"x": 23.921971252566735, "y": "C"}, {"x": 18.548939082819988, "y": "G"}, {"x": 9.308692676249144, "y": "F"}, {"x": 6.5366187542778915, "y": "D"}, {"x": 5.475701574264202, "y": "Am"}, {"x": 4.209445585215605, "y": "A"}, {"x": 3.0116358658453115, "y": "Em"}, {"x": 2.943189596167009, "y": "Dm"}, {"x": 2.3613963039014374, "y": "Gm"}, {"x": 1.7111567419575633, "y": "E"}, {"x": 1.5742642026009583, "y": "Bb"}, {"x": 1.0951403148528405, "y": "Cm"}, {"x": 0.8898015058179329, "y": "Eb"}, {"x": 0.5817932922655715, "y": "Bm"}, {"x": 0.5133470225872689, "y": "F#m"}], "totals": {"chords": 439, "chord_sets": 1976, "keys": 29, "songs": 2922}}